Workbook

Sheet Read Me
B2: Band of One: Affiliate opportunities & disclosure kit
B3: Terms captured from each program's official page on 2026-09-24. Re-verify before applying and every 90 days (see 'Days since verified').
B5: RULES
B6: 1. You have NOT been accepted into any program. Every status starts as 'Not applied'.
B7: 2. Never put an affiliate link on the site, in emails or in posts until the program has issued it to you. Until then the 'Issued link' column says [NOT ISSUED: do not use].
B8: 3. When a link is issued: paste it into 'Issued link', set Status = Approved, then use the 'Link Placeholder Map' tab to see which articles can be updated.
B9: 4. Every article with an affiliate link gets `affiliate: true` in its front matter (this shows the disclosure box) and '(affiliate link)' next to each link. Use rel="sponsored".
B10: 5. Commission never decides a recommendation. If a free or non-affiliate option is better, say so.
B11: 6. Don't use affiliate links in places a program forbids (some ban links in paid ads, emails or on coupon sites). Read each program's terms.
B12: 7. FTC guidance: disclose material connections clearly and conspicuously: https://www.ftc.gov/business-guidance/resources/ftcs-endorsement-guides-what-people-are-asking
B14: TABS
B15: Programs: verified terms + your application tracker (yellow = you fill in).
... B20: No commission amounts, conversion rates or earnings are projected anywhere in this workbook.

Sheet Programs
A1: Company | B1: Program | C1: Official program page | D1: How to apply | E1: Commission (as published) | F1: Cookie / attribution window | G1: Payout threshold & method | H1: Geographic restrictions | I1: Approval requirements | J1: Relevant content topics | K1: Program-specific notes / disclosure rules | L1: Verification | M1: Last verified | N1: Days since verified | O1: Re-verify? | P1: Status | Q1: Date applied | R1: Issued link | S1: Notes
A2: MailerLite | B2: MailerLite Affiliate Program | C2: https://www.mailerlite.com/affiliate | D2: mailerlite.trackdesk.com/sign-up | E2: 30% recurring (lifetime of referral) | F2: 45 days | G2: $100 minimum open balance from at least 2 unique sales; settled Fridays; 30-day on-hold period | H2: Not stated on page: check terms at signup | I2: Application reviewed (up to 10 business days) | J2: Newsletter tools; mailerlite-vs-kit-vs-beehiiv; minimum-tool-stack | K2: Program terms page: mailerlite.com/legal/affiliate-program-terms | L2: Verified official page | M2: 46289 | N2: =IF(M2="","",TODAY()-M2) -> 0 | O2: =IF(N2="","",IF(N2>90,"Re-verify","OK")) -> OK | P2: Not applied | R2: [NOT ISSUED: do not use]
A3: Kit | B3: Kit Affiliate Program | C3: https://kit.com/affiliate | D3: dash.partnerstack.com/application?company=kit&group=kitaffiliates | E3: 50% for first 12 months; 10–20% recurring after 12 months with status tiers | F3: Not stated | G3: $5 threshold; paid around the 13th monthly (Stripe/PayPal/direct deposit); 31-day hold | H3: Not stated on page: check terms at signup | I3: Applications reviewed individually; no audience-size requirement stated | J3: Newsletter tools; creator email | K3: Via PartnerStack | L3: Verified official page | M3: 46289 | N3: =IF(M3="","",TODAY()-M3) -> 0 | O3: =IF(N3="","",IF(N3>90,"Re-verify","OK")) -> OK | P3: Not applied | R3: [NOT ISSUED: do not use]
A4: beehiiv | B4: beehiiv Partner Program | C4: https://www.beehiiv.com/partners/affiliate | D4: app.beehiiv.com/partner_program | E4: Up to 60% of referral's payments for 12 months | F4: 60 days | G4: Paid on the 15th for the prior month (threshold not captured) | H4: Not stated on page: check terms at signup | I4: Not stated on page: check terms at signup | J4: Newsletter platforms comparison | K4: Managed via Dub.co | L4: Verified official page | M4: 46289 | N4: =IF(M4="","",TODAY()-M4) -> 0 | O4: =IF(N4="","",IF(N4>90,"Re-verify","OK")) -> OK | P4: Not applied | R4: [NOT ISSUED: do not use]
A5: Notion | B5: Notion Affiliate Program | C5: https://www.notion.com/affiliates | D5: Via PartnerStack (link on official page) | E5: Up to $50 per activated signup + 20% of year-one revenue | F5: 180 days | G5: Not stated on page: check terms at signup | H5: Not stated on page: check terms at signup | I5: Application (audience types listed on page) | J5: Client tracking; spreadsheet-vs-notion-vs-crm; SOP storage | K5: Via PartnerStack | L5: Verified official page | M5: 46289 | N5: =IF(M5="","",TODAY()-M5) -> 0 | O5: =IF(N5="","",IF(N5>90,"Re-verify","OK")) -> OK | P5: Not applied | R5: [NOT ISSUED: do not use]
A6: Make | B6: Make Affiliate Program | C6: https://www.make.com/en/affiliate | D6: make.com/user/affiliate | E6: 35% for 12 months | F6: 30 days | G6: $100 minimum; paid via Wise | H6: Not stated on page: check terms at signup | I6: Open to anyone with a Make account (per page) | J6: Automation; make-vs-zapier-vs-n8n; what-to-automate-first | L6: Verified official page | M6: 46289 | N6: =IF(M6="","",TODAY()-M6) -> 0 | O6: =IF(N6="","",IF(N6>90,"Re-verify","OK")) -> OK | P6: Not applied | R6: [NOT ISSUED: do not use]
A7: n8n | B7: n8n Affiliate Program | C7: https://n8n.io/affiliates | D7: dash.partnerstack.com/application?company=n8n&group=affiliates2025 | E7: 30% of n8n Cloud referrals for the first year | F7: Not stated | G7: Monthly payouts ≥ EUR 100 via PayPal | H7: Not stated on page: check terms at signup | I7: Application via PartnerStack | J7: Automation comparison | K7: Cloud plans only (self-hosted is free) | L7: Verified official page | M7: 46289 | N7: =IF(M7="","",TODAY()-M7) -> 0 | O7: =IF(N7="","",IF(N7>90,"Re-verify","OK")) -> OK | P7: Not applied | R7: [NOT ISSUED: do not use]
A8: Tally | B8: Tally Referral Program | C8: https://tally.so/help/referral-program | D8: Tally dashboard → Rewards (needs a Tally account) | E8: 20% of subscription payments, capped at $150 per referred user | F8: Not stated | G8: PayPal or Venmo (threshold not captured) | H8: Not stated on page: check terms at signup | I8: No paid plan needed; self-referrals not allowed | J8: Intake forms; client-intake-form-tools; onboarding | K8: Referral program (not a classic affiliate network) | L8: Verified official page | M8: 46289 | N8: =IF(M8="","",TODAY()-M8) -> 0 | O8: =IF(N8="","",IF(N8>90,"Re-verify","OK")) -> OK | P8: Not applied | R8: [NOT ISSUED: do not use]
A9: Dubsado | B9: Dubsado Affiliate Program | C9: https://www.dubsado.com/affiliate-program | D9: app.dubsado.com/user/signup | E9: $35 per referral that stays on a paid plan for 60 days | F9: Not stated | G9: Not stated on page: check terms at signup | H9: Not stated on page: check terms at signup | I9: Open to anyone, including free-trial users (per page) | J9: Client management (CRM) comparisons | L9: Verified official page | M9: 46289 | N9: =IF(M9="","",TODAY()-M9) -> 0 | O9: =IF(N9="","",IF(N9>90,"Re-verify","OK")) -> OK | P9: Not applied | R9: [NOT ISSUED: do not use]
A10: Bonsai | B10: Bonsai Affiliate Program | C10: https://www.hellobonsai.com/affiliates | D10: hellobonsai.firstpromoter.com | E10: 200% of first monthly payment (monthly plans); 30% (yearly plans) | F10: 60 days | G10: Monthly payouts (threshold not captured) | H10: Not stated on page: check terms at signup | I10: Not stated on page: check terms at signup | J10: Invoicing/CRM for freelancers | K10: Via FirstPromoter | L10: Verified official page | M10: 46289 | N10: =IF(M10="","",TODAY()-M10) -> 0 | O10: =IF(N10="","",IF(N10>90,"Re-verify","OK")) -> OK | P10: Not applied | R10: [NOT ISSUED: do not use]
A11: HoneyBook | B11: HoneyBook Referral Program | C11: https://www.honeybook.com/partnerships/referrals | D11: Via HoneyBook account | E11: $100 per paid subscriber + milestone bonuses; described as a limited-time offer | F11: Not stated | G11: 1099-NEC issued if ≥ $600/year (US) | H11: US-focused (verify) | I11: Existing HoneyBook user referral | J11: Client management comparisons | K11: 'Limited time offer, terms apply': re-check before relying on it | L11: Verified official page | M11: 46289 | N11: =IF(M11="","",TODAY()-M11) -> 0 | O11: =IF(N11="","",IF(N11>90,"Re-verify","OK")) -> OK | P11: Not applied | R11: [NOT ISSUED: do not use]
A12: Buffer | B12: Buffer Partner/Affiliate Program | C12: https://buffer.com/partners | D12: Via official page | E12: 25% on new customers for 12 months (only when the referral pays) | F12: Not stated | G12: Not stated on page: check terms at signup | H12: Not stated on page: check terms at signup | I12: Not stated on page: check terms at signup | J12: Social scheduling (marketing articles, future) | L12: Verified official page | M12: 46289 | N12: =IF(M12="","",TODAY()-M12) -> 0 | O12: =IF(N12="","",IF(N12>90,"Re-verify","OK")) -> OK | P12: Not applied | R12: [NOT ISSUED: do not use]
A13: Hostinger | B13: Hostinger Affiliate Program | C13: https://www.hostinger.com/affiliates | D13: affiliates.hostinger.com | E13: At least 40% per eligible sale; rises with volume | F13: Not stated | G13: Not stated on page: check terms at signup | H13: Not stated on page: check terms at signup | I13: Not stated on page: check terms at signup | J13: Website hosting (only if you write hosting content) | L13: Verified official page | M13: 46289 | N13: =IF(M13="","",TODAY()-M13) -> 0 | O13: =IF(N13="","",IF(N13>90,"Re-verify","OK")) -> OK | P13: Not applied | R13: [NOT ISSUED: do not use]
A14: Descript | B14: Descript Affiliate Program | C14: https://www.descript.com/affiliate | D14: Via PartnerStack | E14: $25 flat per new qualifying subscription | F14: Not stated | G14: Paid via PayPal | H14: Not stated on page: check terms at signup | I14: Not stated on page: check terms at signup | J14: Video/podcast editing (social content workflow) | K14: Terms: descript.com/affiliate-terms | L14: Verified official page | M14: 46289 | N14: =IF(M14="","",TODAY()-M14) -> 0 | O14: =IF(N14="","",IF(N14>90,"Re-verify","OK")) -> OK | P14: Not applied | R14: [NOT ISSUED: do not use]
A15: Amazon | B15: Amazon Associates (US) | C15: https://affiliate-program.amazon.com/ | D15: affiliate-program.amazon.com | E15: Fixed rate table by category, e.g. Physical Books 4.50% | F15: Per Amazon policy | G15: Per Amazon policy | H15: Per-marketplace programs | I15: Application; sales requirements apply (check operating agreement) | J15: Book recommendations (business books) | K15: Amazon requires specific disclosure wording: check the Operating Agreement | L15: Verified official page (rate table) | M15: 46289 | N15: =IF(M15="","",TODAY()-M15) -> 0 | O15: =IF(N15="","",IF(N15>90,"Re-verify","OK")) -> OK | P15: Not applied | R15: [NOT ISSUED: do not use]
A16: Fathom | B16: Fathom Growth Partner Program | C16: https://fathom.ai/program/growth-partner | D16: Via PartnerStack | E16: Terms not captured | F16: Not captured | G16: Not captured | H16: Not stated on page: check terms at signup | I16: For agencies and consultants | J16: AI meeting notes (future) | L16: Partially verified: page exists, terms not captured | M16: 46289 | N16: =IF(M16="","",TODAY()-M16) -> 0 | O16: =IF(N16="","",IF(N16>90,"Re-verify","OK")) -> OK | P16: Not applied | R16: [NOT ISSUED: do not use]

Sheet Link Placeholder Map
A1: Article slug | B1: Tool | C1: Official link used today | D1: Placeholder ID | E1: Program status | F1: Issued link | G1: Action
A2: mailerlite-vs-kit-vs-beehiiv | B2: MailerLite | C2: https://www.mailerlite.com/pricing | D2: AFF_MAILERLITE | E2: =IFERROR(INDEX(Programs!$P$2:$P$16,MATCH(B2,Programs!$A$2:$A$16,0)),"No program") -> Not applied | F2: =IFERROR(INDEX(Programs!$R$2:$R$16,MATCH(B2,Programs!$A$2:$A$16,0)),"") -> [NOT ISSUED: do not use] | G2: =IF(AND(E2="Approved",F2<>"",F2<>"[NOT ISSUED: do not use]"),"Allowed: swap link, label (affiliate link), set affiliate: true","Keep the official link") -> Keep the official link
A3: mailerlite-vs-kit-vs-beehiiv | B3: Kit | C3: https://kit.com/pricing | D3: AFF_KIT | E3: =IFERROR(INDEX(Programs!$P$2:$P$16,MATCH(B3,Programs!$A$2:$A$16,0)),"No program") -> Not applied | F3: =IFERROR(INDEX(Programs!$R$2:$R$16,MATCH(B3,Programs!$A$2:$A$16,0)),"") -> [NOT ISSUED: do not use] | G3: =IF(AND(E3="Approved",F3<>"",F3<>"[NOT ISSUED: do not use]"),"Allowed: swap link, label (affiliate link), set affiliate: true","Keep the official link") -> Keep the official link
A4: mailerlite-vs-kit-vs-beehiiv | B4: beehiiv | C4: https://www.beehiiv.com/pricing | D4: AFF_BEEHIIV | E4: =IFERROR(INDEX(Programs!$P$2:$P$16,MATCH(B4,Programs!$A$2:$A$16,0)),"No program") -> Not applied | F4: =IFERROR(INDEX(Programs!$R$2:$R$16,MATCH(B4,Programs!$A$2:$A$16,0)),"") -> [NOT ISSUED: do not use] | G4: =IF(AND(E4="Approved",F4<>"",F4<>"[NOT ISSUED: do not use]"),"Allowed: swap link, label (affiliate link), set affiliate: true","Keep the official link") -> Keep the official link
A5: minimum-tool-stack | B5: MailerLite | C5: https://www.mailerlite.com/pricing | D5: AFF_MAILERLITE | E5: =IFERROR(INDEX(Programs!$P$2:$P$16,MATCH(B5,Programs!$A$2:$A$16,0)),"No program") -> Not applied | F5: =IFERROR(INDEX(Programs!$R$2:$R$16,MATCH(B5,Programs!$A$2:$A$16,0)),"") -> [NOT ISSUED: do not use] | G5: =IF(AND(E5="Approved",F5<>"",F5<>"[NOT ISSUED: do not use]"),"Allowed: swap link, label (affiliate link), set affiliate: true","Keep the official link") -> Keep the official link
A6: minimum-tool-stack | B6: Kit | C6: https://kit.com/pricing | D6: AFF_KIT | E6: =IFERROR(INDEX(Programs!$P$2:$P$16,MATCH(B6,Programs!$A$2:$A$16,0)),"No program") -> Not applied | F6: =IFERROR(INDEX(Programs!$R$2:$R$16,MATCH(B6,Programs!$A$2:$A$16,0)),"") -> [NOT ISSUED: do not use] | G6: =IF(AND(E6="Approved",F6<>"",F6<>"[NOT ISSUED: do not use]"),"Allowed: swap link, label (affiliate link), set affiliate: true","Keep the official link") -> Keep the official link
A7: minimum-tool-stack | B7: Tally | C7: https://tally.so/pricing | D7: AFF_TALLY | E7: =IFERROR(INDEX(Programs!$P$2:$P$16,MATCH(B7,Programs!$A$2:$A$16,0)),"No program") -> Not applied | F7: =IFERROR(INDEX(Programs!$R$2:$R$16,MATCH(B7,Programs!$A$2:$A$16,0)),"") -> [NOT ISSUED: do not use] | G7: =IF(AND(E7="Approved",F7<>"",F7<>"[NOT ISSUED: do not use]"),"Allowed: swap link, label (affiliate link), set affiliate: true","Keep the official link") -> Keep the official link
A8: minimum-tool-stack | B8: Notion | C8: https://www.notion.com/pricing | D8: AFF_NOTION | E8: =IFERROR(INDEX(Programs!$P$2:$P$16,MATCH(B8,Programs!$A$2:$A$16,0)),"No program") -> Not applied | F8: =IFERROR(INDEX(Programs!$R$2:$R$16,MATCH(B8,Programs!$A$2:$A$16,0)),"") -> [NOT ISSUED: do not use] | G8: =IF(AND(E8="Approved",F8<>"",F8<>"[NOT ISSUED: do not use]"),"Allowed: swap link, label (affiliate link), set affiliate: true","Keep the official link") -> Keep the official link
A9: minimum-tool-stack | B9: Make | C9: https://www.make.com/en/pricing | D9: AFF_MAKE | E9: =IFERROR(INDEX(Programs!$P$2:$P$16,MATCH(B9,Programs!$A$2:$A$16,0)),"No program") -> Not applied | F9: =IFERROR(INDEX(Programs!$R$2:$R$16,MATCH(B9,Programs!$A$2:$A$16,0)),"") -> [NOT ISSUED: do not use] | G9: =IF(AND(E9="Approved",F9<>"",F9<>"[NOT ISSUED: do not use]"),"Allowed: swap link, label (affiliate link), set affiliate: true","Keep the official link") -> Keep the official link
A10: make-vs-zapier-vs-n8n | B10: Make | C10: https://www.make.com/en/pricing | D10: AFF_MAKE | E10: =IFERROR(INDEX(Programs!$P$2:$P$16,MATCH(B10,Programs!$A$2:$A$16,0)),"No program") -> Not applied | F10: =IFERROR(INDEX(Programs!$R$2:$R$16,MATCH(B10,Programs!$A$2:$A$16,0)),"") -> [NOT ISSUED: do not use] | G10: =IF(AND(E10="Approved",F10<>"",F10<>"[NOT ISSUED: do not use]"),"Allowed: swap link, label (affiliate link), set affiliate: true","Keep the official link") -> Keep the official link
A11: make-vs-zapier-vs-n8n | B11: n8n | C11: https://n8n.io/pricing/ | D11: AFF_N8N | E11: =IFERROR(INDEX(Programs!$P$2:$P$16,MATCH(B11,Programs!$A$2:$A$16,0)),"No program") -> Not applied | F11: =IFERROR(INDEX(Programs!$R$2:$R$16,MATCH(B11,Programs!$A$2:$A$16,0)),"") -> [NOT ISSUED: do not use] | G11: =IF(AND(E11="Approved",F11<>"",F11<>"[NOT ISSUED: do not use]"),"Allowed: swap link, label (affiliate link), set affiliate: true","Keep the official link") -> Keep the official link
A12: what-to-automate-first | B12: Make | C12: https://www.make.com/en/pricing | D12: AFF_MAKE | E12: =IFERROR(INDEX(Programs!$P$2:$P$16,MATCH(B12,Programs!$A$2:$A$16,0)),"No program") -> Not applied | F12: =IFERROR(INDEX(Programs!$R$2:$R$16,MATCH(B12,Programs!$A$2:$A$16,0)),"") -> [NOT ISSUED: do not use] | G12: =IF(AND(E12="Approved",F12<>"",F12<>"[NOT ISSUED: do not use]"),"Allowed: swap link, label (affiliate link), set affiliate: true","Keep the official link") -> Keep the official link
A13: client-intake-form-tools | B13: Tally | C13: https://tally.so/pricing | D13: AFF_TALLY | E13: =IFERROR(INDEX(Programs!$P$2:$P$16,MATCH(B13,Programs!$A$2:$A$16,0)),"No program") -> Not applied | F13: =IFERROR(INDEX(Programs!$R$2:$R$16,MATCH(B13,Programs!$A$2:$A$16,0)),"") -> [NOT ISSUED: do not use] | G13: =IF(AND(E13="Approved",F13<>"",F13<>"[NOT ISSUED: do not use]"),"Allowed: swap link, label (affiliate link), set affiliate: true","Keep the official link") -> Keep the official link
... A15: client-onboarding-checklist | B15: Tally | C15: https://tally.so/pricing | D15: AFF_TALLY | E15: =IFERROR(INDEX(Programs!$P$2:$P$16,MATCH(B15,Programs!$A$2:$A$16,0)),"No program") -> Not applied | F15: =IFERROR(INDEX(Programs!$R$2:$R$16,MATCH(B15,Programs!$A$2:$A$16,0)),"") -> [NOT ISSUED: do not use] | G15: =IF(AND(E15="Approved",F15<>"",F15<>"[NOT ISSUED: do not use]"),"Allowed: swap link, label (affiliate link), set affiliate: true","Keep the official link") -> Keep the official link

Sheet Disclosure Language
A1: Where | B1: Type | C1: Copy-paste text
A2: Site-wide page | B2: Affiliate disclosure page | C2: Already live on the website draft: /affiliate-disclosure/ (currently states that there are no affiliate links).
A3: Top of article (before first link) | B3: Article disclosure box | C3: Disclosure: this article contains affiliate links, marked "(affiliate link)". If you buy through one, we may earn a commission at no extra cost to you. It never changes our recommendations.
A4: Next to each link | B4: Inline label | C4: Tool name (affiliate link)
A5: Tool comparison intro | B5: Relationship statement | C5: We're an affiliate for [TOOL A] and [TOOL B], which means we may earn a commission if you sign up through our links. We have no relationship with [TOOL C]. Our ratings are the same either way.
A6: Email newsletter | B6: Email line | C6: This email contains an affiliate link to [TOOL]. If you sign up through it, I may earn a commission at no extra cost to you.
A7: Social post (text) | B7: Post disclosure | C7: #ad: I earn a commission if you sign up through this link. I use/recommend it because [honest reason].
A8: Video / short-form | B8: Spoken + on-screen | C8: Say it out loud near the start ("This video includes an affiliate link") AND show it on screen; a caption alone may be missed.
A9: Own products | B9: Own-product statement | C9: This is a product we make and sell.
A10: Amazon links | B10: Amazon required wording | C10: As an Amazon Associate I earn from qualifying purchases. (Check the current Operating Agreement for the exact wording required.)

Sheet Not Available
A1: Company | B1: Finding (checked 2026-09-24) | C1: Page checked
A2: Canva | B2: Affiliate program replaced by 'Canvassador'; closed to applications when checked | C2: canva.com/help/canva-affiliate-marketing-program
A3: Zapier | B3: No public affiliate page found (zapier.com/affiliates returned 404) | C3: zapier.com/affiliates
A4: Motion | B4: Affiliate page returned 404 | C4: usemotion.com/affiliate-program
A5: Jotform | B5: Affiliate page returned 404 | C5: jotform.com/affiliate-program/
A6: ClickUp | B6: Site blocked our check (403). A third-party summary claimed terms we could NOT verify: treat as unknown | C6: clickup.com
A7: ChatGPT / Claude / Gemini | B7: No consumer affiliate programs identified; not researched further | C7: -
A8: Google Forms | B8: No affiliate program (free Google product) | C8: -
