Workbook

Sheet Assumptions
B1: Band of One: Pricing calculator
B2: Blue text on yellow = inputs you can change. Black = formulas. Green = links to this sheet from other tabs. No sales forecasts: this workbook only does per-sale and break-even math.
B4: Assumption | C4: Value | D4: Notes / source
B5: Gumroad fee on direct sales (percent) | C5: 0.1 | D5: Source: Gumroad Help, 'Gumroad's fees' (gumroad.com/help/article/66-gumroads-fees), checked 2026-09-24.
B6: Gumroad fee on direct sales (fixed, per sale) | C6: 0.5 | D6: Source: Gumroad Help, 'Gumroad's fees' (gumroad.com/help/article/66-gumroads-fees), checked 2026-09-24.
B7: Card processing (percent) | C7: 0.029 | D7: Source: Gumroad Help, 'Gumroad's fees' (gumroad.com/help/article/66-gumroads-fees), checked 2026-09-24. PayPal fees differ; card rate used as the base case.
B8: Card processing (fixed, per sale) | C8: 0.3 | D8: Source: Gumroad Help, 'Gumroad's fees' (gumroad.com/help/article/66-gumroads-fees), checked 2026-09-24.
B9: Gumroad Discover marketplace fee (flat, incl. processing) | C9: 0.3 | D9: Source: Gumroad Help, 'Gumroad's fees' (gumroad.com/help/article/66-gumroads-fees), checked 2026-09-24. Applies only to sales Gumroad's marketplace brings you.
B10: Refund rate (assumption) | C10: 0.05 | D10: ASSUMPTION, not data: 5% of sales refunded. Replace with your real rate after 30+ sales (Dashboard → Refunds).
B11: Affiliate commission (if an affiliate made the sale) | C11: 0 | D11: 0% by default. Gumroad lets you set 1–75%; fees are shared in proportion (gumroad.com/help/article/333). Try 30% to see the effect.
B12: Monthly tool costs to cover | C12: 0 | D12: Launch plan costs $0/month. Example: MailerLite Comfort is $10.80/mo billed yearly for 500 subscribers (mailerlite.com/pricing, checked 2026-09-24).
B14: Refund math used: Gumroad returns its own fee on the refunded amount but keeps the card-processing portion (same source). So a refunded sale costs you the processing fee.
B15: Sales tax/VAT: the calculator treats your price as tax-exclusive revenue. Check Gumroad's current tax help pages for how tax is collected in your buyers' locations.

Sheet Per-sale math
B1: What you keep from one sale
B2: Prices are inputs (blue on yellow). Everything else is calculated from the Assumptions tab.
B4: Product | C4: Price tier | D4: Price | E4: Gumroad fee | F4: Processing | G4: Net: direct sale | H4: Fees as % of price | I4: Net: Discover sale | J4: Expected net per sale after refunds | K4: Net if affiliate sale | L4: Sales/month to cover tools
B5: A · The Solo Admin Playbook | C5: Intro | D5: 19 | E5: =D5*Assumptions!$C$5+Assumptions!$C$6 -> 2.4 | F5: =D5*Assumptions!$C$7+Assumptions!$C$8 -> 0.851 | G5: =D5-E5-F5 -> 15.749 | H5: =IF(D5=0,0,(E5+F5)/D5) -> 0.17110526 | I5: =D5*(1-Assumptions!$C$9) -> 13.3 | J5: =(1-Assumptions!$C$10)*G5-Assumptions!$C$10*F5 -> 14.919 | K5: =G5*(1-Assumptions!$C$11) -> 15.749 | L5: =IF(Assumptions!$C$12=0,0,IF(J5<=0,"n/a",ROUNDUP(Assumptions!$C$12/J5,0))) -> 0
B6: A · The Solo Admin Playbook | C6: Regular | D6: 24 | E6: =D6*Assumptions!$C$5+Assumptions!$C$6 -> 2.9 | F6: =D6*Assumptions!$C$7+Assumptions!$C$8 -> 0.996 | G6: =D6-E6-F6 -> 20.104 | H6: =IF(D6=0,0,(E6+F6)/D6) -> 0.16233333 | I6: =D6*(1-Assumptions!$C$9) -> 16.8 | J6: =(1-Assumptions!$C$10)*G6-Assumptions!$C$10*F6 -> 19.049 | K6: =G6*(1-Assumptions!$C$11) -> 20.104 | L6: =IF(Assumptions!$C$12=0,0,IF(J6<=0,"n/a",ROUNDUP(Assumptions!$C$12/J6,0))) -> 0
B7: B · The Client Desk | C7: Intro | D7: 24 | E7: =D7*Assumptions!$C$5+Assumptions!$C$6 -> 2.9 | F7: =D7*Assumptions!$C$7+Assumptions!$C$8 -> 0.996 | G7: =D7-E7-F7 -> 20.104 | H7: =IF(D7=0,0,(E7+F7)/D7) -> 0.16233333 | I7: =D7*(1-Assumptions!$C$9) -> 16.8 | J7: =(1-Assumptions!$C$10)*G7-Assumptions!$C$10*F7 -> 19.049 | K7: =G7*(1-Assumptions!$C$11) -> 20.104 | L7: =IF(Assumptions!$C$12=0,0,IF(J7<=0,"n/a",ROUNDUP(Assumptions!$C$12/J7,0))) -> 0
B8: B · The Client Desk | C8: Regular | D8: 29 | E8: =D8*Assumptions!$C$5+Assumptions!$C$6 -> 3.4 | F8: =D8*Assumptions!$C$7+Assumptions!$C$8 -> 1.141 | G8: =D8-E8-F8 -> 24.459 | H8: =IF(D8=0,0,(E8+F8)/D8) -> 0.15658621 | I8: =D8*(1-Assumptions!$C$9) -> 20.3 | J8: =(1-Assumptions!$C$10)*G8-Assumptions!$C$10*F8 -> 23.179 | K8: =G8*(1-Assumptions!$C$11) -> 24.459 | L8: =IF(Assumptions!$C$12=0,0,IF(J8<=0,"n/a",ROUNDUP(Assumptions!$C$12/J8,0))) -> 0
B9: C · The Band of One Prompt Library | C9: Intro | D9: 15 | E9: =D9*Assumptions!$C$5+Assumptions!$C$6 -> 2 | F9: =D9*Assumptions!$C$7+Assumptions!$C$8 -> 0.735 | G9: =D9-E9-F9 -> 12.265 | H9: =IF(D9=0,0,(E9+F9)/D9) -> 0.18233333 | I9: =D9*(1-Assumptions!$C$9) -> 10.5 | J9: =(1-Assumptions!$C$10)*G9-Assumptions!$C$10*F9 -> 11.615 | K9: =G9*(1-Assumptions!$C$11) -> 12.265 | L9: =IF(Assumptions!$C$12=0,0,IF(J9<=0,"n/a",ROUNDUP(Assumptions!$C$12/J9,0))) -> 0
B10: C · The Band of One Prompt Library | C10: Regular | D10: 19 | E10: =D10*Assumptions!$C$5+Assumptions!$C$6 -> 2.4 | F10: =D10*Assumptions!$C$7+Assumptions!$C$8 -> 0.851 | G10: =D10-E10-F10 -> 15.749 | H10: =IF(D10=0,0,(E10+F10)/D10) -> 0.17110526 | I10: =D10*(1-Assumptions!$C$9) -> 13.3 | J10: =(1-Assumptions!$C$10)*G10-Assumptions!$C$10*F10 -> 14.919 | K10: =G10*(1-Assumptions!$C$11) -> 15.749 | L10: =IF(Assumptions!$C$12=0,0,IF(J10<=0,"n/a",ROUNDUP(Assumptions!$C$12/J10,0))) -> 0
B11: Bundle · All three products | C11: Intro | D11: 39 | E11: =D11*Assumptions!$C$5+Assumptions!$C$6 -> 4.4 | F11: =D11*Assumptions!$C$7+Assumptions!$C$8 -> 1.431 | G11: =D11-E11-F11 -> 33.169 | H11: =IF(D11=0,0,(E11+F11)/D11) -> 0.14951282 | I11: =D11*(1-Assumptions!$C$9) -> 27.3 | J11: =(1-Assumptions!$C$10)*G11-Assumptions!$C$10*F11 -> 31.439 | K11: =G11*(1-Assumptions!$C$11) -> 33.169 | L11: =IF(Assumptions!$C$12=0,0,IF(J11<=0,"n/a",ROUNDUP(Assumptions!$C$12/J11,0))) -> 0
B12: Bundle · All three products | C12: Regular | D12: 49 | E12: =D12*Assumptions!$C$5+Assumptions!$C$6 -> 5.4 | F12: =D12*Assumptions!$C$7+Assumptions!$C$8 -> 1.721 | G12: =D12-E12-F12 -> 41.879 | H12: =IF(D12=0,0,(E12+F12)/D12) -> 0.14532653 | I12: =D12*(1-Assumptions!$C$9) -> 34.3 | J12: =(1-Assumptions!$C$10)*G12-Assumptions!$C$10*F12 -> 39.699 | K12: =G12*(1-Assumptions!$C$11) -> 41.879 | L12: =IF(Assumptions!$C$12=0,0,IF(J12<=0,"n/a",ROUNDUP(Assumptions!$C$12/J12,0))) -> 0
B14: Bundle saving vs. buying all three separately
C15: Intro | D15: =(D5+D7+D9)-D11 -> 19 | E15: =IF((D5+D7+D9)=0,0,D15/(D5+D7+D9)) -> 0.32758621 | F15: saved / % off
C16: Regular | D16: =(D6+D8+D10)-D12 -> 23 | E16: =IF((D6+D8+D10)=0,0,D16/(D6+D8+D10)) -> 0.31944444 | F16: saved / % off

Sheet Market price evidence
B1: Observed prices of comparable listings (snapshot 2026-09-24; Etsy prices can include temporary sales)
B3: Comparable to | C3: Listing (as shown) | D3: Price shown (USD) | E3: Where
B4: C · Prompt Library | C4: 100 AI Prompts for Etsy Sellers | ChatGPT Claude Gemini Prompt Pack | D4: 5.49 | E4: Etsy search 'chatgpt prompts small business'
B5: C · Prompt Library | C5: ChatGPT Prompts for Work & Business (100) | D5: 8.99 | E5: Etsy search 'chatgpt prompts small business'
B6: C · Prompt Library | C6: Claude AI Skill Pack | 1000 Skills for Small Business | D6: 14.67 | E6: Etsy search 'chatgpt prompts small business'
B7: C · Prompt Library | C7: ChatGPT Prompts for Small Business 210+ AI Automation Templates | D7: 19 | E7: Etsy search 'chatgpt prompts small business'
B8: B · Client Desk | C8: Client Tracker Excel CRM (inDeoDesignStudio) | D8: 18.71 | E8: Etsy search 'freelance client tracker spreadsheet'
B9: B · Client Desk | C9: Notion Freelancer Template CRM (GraceAndGrow) | D9: 23.55 | E9: Etsy search 'freelance client tracker spreadsheet'
B10: B · Client Desk | C10: Real estate transaction tracker | D10: 24.99 | E10: Etsy search 'freelance client tracker spreadsheet'
B11: A · Playbook / Bundle | C11: Client onboarding Canva bundle (AmmaRoseDesigns) | D11: 37 | E11: Etsy search 'client onboarding template freelancer'
B12: A · Playbook / Bundle | C12: Creative Business Hub (Notion) | D12: 97 | E12: Etsy search 'client onboarding template freelancer'
B14: Full list: Digital_Products_Business/01_Market_Research/Marketplace_Observations_2026-09-24.csv
