Workbook

Sheet Calendar
A1: Band of One: 60-day social calendar (Month 1 content → Month 2 product launch)
A2: Start date (Day 1): | E2: Type your Day 1 date in the yellow cell; every date below updates. Launch day = Day 38 (Month 2, day 8). Nothing is scheduled or posted automatically.
A4: Day | B4: Date | C4: Weekday | D4: Campaign month | E4: Channel | F4: Type | G4: ID | H4: Title / concept | I4: Hook | J4: Link | K4: Caption / post text | L4: Hashtags | M4: Graphic | N4: Status | O4: Posted URL | P4: Notes
A5: 1 | B5: =IF($C$2="","",$C$2+A5-1) | C5: =IF(B5="","",TEXT(B5,"ddd")) | D5: Month 1: Content | E5: LinkedIn | F5: Educational post | G5: C-E01 | H5: The onboarding checklist | J5: /blog/client-onboarding-checklist/ | K5: Most client problems start in week one, not week ten. A 7-step onboarding checklist that prevents most of them: 1. Proposal accepted in writing 2. Agreement signed (scope, exclusions, payment terms, revisions) 3. Deposit invoice sent. Work starts when it clears 4. Welcome email with numbered next steps 5. Intake form instead of 20 questions by email 6. Communication norms agreed: where, when, how fast 7. Kickoff call with an agenda, plus a written summary the same day Same steps, same order, every client. After three clients you'll know which questions to add to your form. Full checklist + free tools: [link] | L5: #freelancetips #clientexperience #smallbusinesstips #solopreneur #consultantlife | N5: Draft
A6: 1 | B6: =IF($C$2="","",$C$2+A6-1) | C6: =IF(B6="","",TEXT(B6,"ddd")) | D6: Month 1: Content | E6: TikTok / Reels / Shorts (+ LinkedIn native) | F6: Short video | G6: C-V01 | H6: The 30-minute onboarding checklist | I6: Most client problems start in the first week, not the last. | J6: /blog/client-onboarding-checklist/ | K6: Most client problems start in week one. Here's the 7-step onboarding checklist I'd give every freelancer: same steps, same order, every client. Full checklist + free tools at the link in bio. | L6: #freelancetips #clientexperience #smallbusinesstips #solopreneur #consultantlife | M6: graphics/video_covers/C-V01.png | N6: Draft
A7: 2 | B7: =IF($C$2="","",$C$2+A7-1) | C7: =IF(B7="","",TEXT(B7,"ddd")) | D7: Month 1: Content | E7: LinkedIn + Instagram | F7: Promotional post | G7: C-P01 | H7: Free starter kit launch | J7: /newsletter/ | K7: New and free: the Client Admin Starter Kit. 10 AI prompts for the admin you do every week (inquiry replies, call summaries, proposals, welcome emails, weekly updates, scope changes, payment reminders, testimonial requests), plus a printable 30-minute weekly review checklist. Works with free AI plans. Get it here: [link] | L7: #bandofone #solopreneur #freelancer #virtualassistant #consultant | M7: graphics/promo_cards/C-P01.png | N7: Draft
A8: 2 | B8: =IF($C$2="","",$C$2+A8-1) | C8: =IF(B8="","",TEXT(B8,"ddd")) | D8: Month 1: Content | E8: TikTok / Reels / Shorts (+ LinkedIn native) | F8: Short video | G8: C-V02 | H8: Never paste these into ChatGPT | I8: Five things that should never go into an AI chat, even for client work. | J8: /blog/client-data-privacy-ai/ | K8: Using AI for client emails? Five things that never go in the chat, plus the 5-second redaction habit for everything else. The settings for ChatGPT, Claude and Gemini are in the full guide (link in bio). | L8: #AItools #ChatGPTtips #AIforBusiness #promptengineering #freelancetips | M8: graphics/video_covers/C-V02.png | N8: Draft
A9: 3 | B9: =IF($C$2="","",$C$2+A9-1) | C9: =IF(B9="","",TEXT(B9,"ddd")) | D9: Month 1: Content | E9: Instagram | F9: Educational post (carousel) | G9: C-E02 | H9: 5 things never to paste into AI | J9: /blog/client-data-privacy-ai/ | K9: Save this for the next time you're about to paste an email thread into an AI chat. The redaction habit takes five seconds, and the full privacy routine (with where to find the ChatGPT, Claude and Gemini settings) is at the link in bio. | L9: #AItools #ChatGPTtips #AIforBusiness #promptengineering #freelancetips | M9: graphics/carousels/C-E02_01.png | N9: Draft
A10: 3 | B10: =IF($C$2="","",$C$2+A10-1) | C10: =IF(B10="","",TEXT(B10,"ddd")) | D10: Month 1: Content | E10: TikTok / Reels / Shorts (+ LinkedIn native) | F10: Short video | G10: C-V03 | H10: The 5-stage payment reminder schedule | I10: Chasing invoices feels personal because you haven't decided the schedule in advance. | J10: /blog/payment-reminder-schedule/ | K10: Chasing invoices gets easier when the schedule is decided in advance. Five stages, five templates, from a friendly heads-up to a final notice. Link in bio. | L10: #freelancebusiness #invoicing #smallbusinessowner #getpaid #solopreneur | M10: graphics/video_covers/C-V03.png | N10: Draft
A11: 4 | B11: =IF($C$2="","",$C$2+A11-1) | C11: =IF(B11="","",TEXT(B11,"ddd")) | D11: Month 1: Content | E11: TikTok / Reels / Shorts (+ LinkedIn native) | F11: Short video | G11: C-V04 | H11: Why your AI emails sound generic | I11: Your AI emails sound generic because the AI knows nothing about your business. | J11: /blog/ai-business-brief/ | K11: If your AI drafts sound generic, it's usually missing context, not a better prompt. Build a one-page business brief once (the interview prompt is in the link in bio) and every draft starts from your reality. | L11: #AItools #ChatGPTtips #AIforBusiness #promptengineering #freelancetips | M11: graphics/video_covers/C-V04.png | N11: Draft
A12: 5 | B12: =IF($C$2="","",$C$2+A12-1) | C12: =IF(B12="","",TEXT(B12,"ddd")) | D12: Month 1: Content | E12: LinkedIn | F12: Educational post | G12: C-E03 | H12: Payment reminders, decided once | J12: /blog/payment-reminder-schedule/ | K12: Chasing invoices feels personal because most of us decide what to do each time. Decide once: A: 3 days before due: friendly heads-up (catches wrong-inbox problems) B: due date: short reminder C: +7 days: "anything holding it up?" D: +14 days: ask for a payment date in writing E: +30 days: final notice, stating only what's in your agreement It matters: in Bonsai's data from 100,000+ freelancers, 29% of invoices were paid at least a day late (Bonsai, updated Jan 2026). Templates for all five stages: [link] | L12: #freelancebusiness #invoicing #smallbusinessowner #getpaid #solopreneur | N12: Draft
A13: 5 | B13: =IF($C$2="","",$C$2+A13-1) | C13: =IF(B13="","",TEXT(B13,"ddd")) | D13: Month 1: Content | E13: TikTok / Reels / Shorts (+ LinkedIn native) | F13: Short video | G13: C-V05 | H13: The weekly client update in 4 headings | I13: Clients chase you when they don't know what's happening. | J13: /blog/weekly-client-update-template/ | K13: The five-minute weekly client update: four headings, same day every week. 'Needed from you (with dates)' is the line that does the heavy lifting. Template + AI prompt at the link in bio. | L13: #freelancetips #clientexperience #smallbusinesstips #solopreneur #consultantlife | M13: graphics/video_covers/C-V05.png | N13: Draft
A14: 6 | B14: =IF($C$2="","",$C$2+A14-1) | C14: =IF(B14="","",TEXT(B14,"ddd")) | D14: Month 1: Content | E14: LinkedIn + Instagram | F14: Promotional post | G14: C-P02 | H14: Free invoice tracker | J14: /blog/track-invoices-in-a-spreadsheet/ | K14: Free download: a small spreadsheet that tells you which payment reminder to send (A–E) for every invoice. Tested against eight scenarios before we published it. Works in Google Sheets and Excel. No sign-up needed. Formulas explained + download: [link] | L14: #freelancebusiness #invoicing #smallbusinessowner #getpaid #solopreneur | M14: graphics/promo_cards/C-P02.png | N14: Draft
A15: 6 | B15: =IF($C$2="","",$C$2+A15-1) | C15: =IF(B15="","",TEXT(B15,"ddd")) | D15: Month 1: Content | E15: TikTok / Reels / Shorts (+ LinkedIn native) | F15: Short video | G15: C-V06 | H15: Score before you automate | I15: Don't automate your admin yet. Score it first. | J15: /blog/what-to-automate-first/ | K15: Before you buy an automation tool, score your admin tasks: (times per month × minutes) × repeatability ÷ risk. Often the best first fix is a template, not a robot. Method + example at the link in bio. | L15: #systemsthinking #SOP #productivitytips #solopreneur #businesssystems | M15: graphics/video_covers/C-V06.png | N15: Draft
A16: 7 | B16: =IF($C$2="","",$C$2+A16-1) | C16: =IF(B16="","",TEXT(B16,"ddd")) | D16: Month 1: Content | E16: Instagram | F16: Educational post (carousel) | G16: C-E04 | H16: The weekly client update | J16: /blog/weekly-client-update-template/ | K16: Four headings, same day every week. The 'Needed from you' line turns vague delays into specific requests with dates. Template + AI prompt at the link in bio. | L16: #freelancetips #clientexperience #smallbusinesstips #solopreneur #consultantlife | M16: graphics/carousels/C-E04_01.png | N16: Draft
A17: 7 | B17: =IF($C$2="","",$C$2+A17-1) | C17: =IF(B17="","",TEXT(B17,"ddd")) | D17: Month 1: Content | E17: TikTok / Reels / Shorts (+ LinkedIn native) | F17: Short video | G17: C-V07 | H17: What Band of One is (intro) | I17: If you run a service business on your own, you're also the whole back office. | J17: /newsletter/ | K17: Band of One: practical AI systems for businesses of one. Workflows, templates and honest tool notes for freelancers, consultants, coaches and VAs. Start with the free starter kit (link in bio). | L17: #bandofone #solopreneur #freelancer #virtualassistant #consultant | M17: graphics/video_covers/C-V07.png | N17: Draft
A18: 8 | B18: =IF($C$2="","",$C$2+A18-1) | C18: =IF(B18="","",TEXT(B18,"ddd")) | D18: Month 1: Content | E18: TikTok / Reels / Shorts (+ LinkedIn native) | F18: Short video | G18: C-V08 | H18: Deposits: the one sentence that matters | I18: The most important sentence in your payment terms is seven words long. | J18: /blog/deposits-and-payment-terms/ | K18: Deposits, milestones and payment terms: decide them once and put them in every proposal. The wording (plus a full example) is at the link in bio. General info, not legal advice. | L18: #freelancebusiness #invoicing #smallbusinessowner #getpaid #solopreneur | M18: graphics/video_covers/C-V08.png | N18: Draft
A19: 9 | B19: =IF($C$2="","",$C$2+A19-1) | C19: =IF(B19="","",TEXT(B19,"ddd")) | D19: Month 1: Content | E19: LinkedIn | F19: Educational post | G19: C-E05 | H19: Why AI drafts sound generic | J19: /blog/ai-business-brief/ | K19: If your AI drafts sound generic, the problem usually isn't the prompt. It's missing context. The assistant doesn't know your services, your terms, or the promises you never make. So it fills the gaps with the average of everything it's read. Fix it once with a one-page business brief: → Who I am → Services → Ideal clients → How I work → Policies → Tone and words to avoid Let the AI interview you to build it (about 20 minutes), then reuse it everywhere. The interview prompt: [link] | L19: #AItools #ChatGPTtips #AIforBusiness #promptengineering #freelancetips | N19: Draft
A20: 9 | B20: =IF($C$2="","",$C$2+A20-1) | C20: =IF(B20="","",TEXT(B20,"ddd")) | D20: Month 1: Content | E20: TikTok / Reels / Shorts (+ LinkedIn native) | F20: Short video | G20: C-V09 | H20: Make AI sound like you | I20: You can spot an AI email from the first line. | J20: /blog/make-ai-sound-like-you/ | K20: "I hope this email finds you well." Here's how to make AI drafts sound like you instead: a voice profile built from 3–5 of your real emails. Prompt and example at the link in bio. | L20: #AItools #ChatGPTtips #AIforBusiness #promptengineering #freelancetips | M20: graphics/video_covers/C-V09.png | N20: Draft
A21: 10 | B21: =IF($C$2="","",$C$2+A21-1) | C21: =IF(B21="","",TEXT(B21,"ddd")) | D21: Month 1: Content | E21: LinkedIn | F21: Promotional post | G21: C-P03 | H21: Why we label tested vs researched | J21: /editorial-policy/ | K21: A small promise from Band of One: every tool article is labeled. Tested = we used it for the job described, and we say how. Researched = based on official docs and pricing pages, with the date checked. No "we tested 50 tools". No income claims. No fake testimonials. Our editorial policy: [link] | L21: #bandofone #solopreneur #freelancer #virtualassistant #consultant | M21: graphics/promo_cards/C-P03.png | N21: Draft
A22: 10 | B22: =IF($C$2="","",$C$2+A22-1) | C22: =IF(B22="","",TEXT(B22,"ddd")) | D22: Month 1: Content | E22: TikTok / Reels / Shorts (+ LinkedIn native) | F22: Short video | G22: C-V10 | H22: Scope creep: offer a choice | I22: Scope creep isn't a people problem. It's a visibility problem. | J22: /blog/scope-creep-email-templates/ | K22: Scope creep is a visibility problem. Name the change, offer two options, wait for a yes. Four email templates (including the "quick favor") at the link in bio. | L22: #freelancetips #clientexperience #smallbusinesstips #solopreneur #consultantlife | M22: graphics/video_covers/C-V10.png | N22: Draft
A23: 11 | B23: =IF($C$2="","",$C$2+A23-1) | C23: =IF(B23="","",TEXT(B23,"ddd")) | D23: Month 1: Content | E23: Instagram | F23: Educational post (carousel) | G23: C-E06 | H23: Score your admin before you automate | J23: /blog/what-to-automate-first/ | K23: The scoring method that stops you spending a weekend automating a task you do twice a month. Worked example at the link in bio. | L23: #systemsthinking #SOP #productivitytips #solopreneur #businesssystems | M23: graphics/carousels/C-E06_01.png | N23: Draft
A24: 11 | B24: =IF($C$2="","",$C$2+A24-1) | C24: =IF(B24="","",TEXT(B24,"ddd")) | D24: Month 1: Content | E24: TikTok / Reels / Shorts (+ LinkedIn native) | F24: Short video | G24: C-V11 | H24: Spreadsheet formula: which reminder is due | I24: One spreadsheet formula can tell you which payment reminder to send. | J24: /blog/track-invoices-in-a-spreadsheet/ | K24: A spreadsheet that tells you which payment reminder to send (A–E). Tested against eight scenarios; works in Google Sheets and Excel. Free starter file at the link in bio. | L24: #freelancebusiness #invoicing #smallbusinessowner #getpaid #solopreneur | M24: graphics/video_covers/C-V11.png | N24: Draft
A25: 12 | B25: =IF($C$2="","",$C$2+A25-1) | C25: =IF(B25="","",TEXT(B25,"ddd")) | D25: Month 1: Content | E25: Instagram | F25: Promotional post | G25: C-P04 | H25: Newsletter: one idea a week | J25: /newsletter/ | K25: One practical admin-system idea a week, by email. Short, useful, no hype. Plus the free starter kit when you sign up. Unsubscribe any time. Link in bio. | L25: #bandofone #solopreneur #freelancer #virtualassistant #consultant | M25: graphics/promo_cards/C-P04.png | N25: Draft
A26: 12 | B26: =IF($C$2="","",$C$2+A26-1) | C26: =IF(B26="","",TEXT(B26,"ddd")) | D26: Month 1: Content | E26: TikTok / Reels / Shorts (+ LinkedIn native) | F26: Short video | G26: C-V12 | H26: The weekly admin review | I26: Admin with no set time leaks into every day. | J26: /blog/weekly-admin-review/ | K26: One 45-minute appointment a week keeps admin out of the rest of your week. The five-block agenda (plus an AI prompt that pre-sorts it) is at the link in bio. | L26: #systemsthinking #SOP #productivitytips #solopreneur #businesssystems | M26: graphics/video_covers/C-V12.png | N26: Draft
A27: 13 | B27: =IF($C$2="","",$C$2+A27-1) | C27: =IF(B27="","",TEXT(B27,"ddd")) | D27: Month 1: Content | E27: LinkedIn | F27: Educational post | G27: C-E07 | H27: Scope creep in one email | J27: /blog/scope-creep-email-templates/ | K27: Scope creep rarely arrives as a big request. It's "while you're in there…" The goal isn't to say no. It's to make the change visible: "Thanks for the idea. It's outside the current scope, so two options: 1) Add it now: [price], and launch moves to [date] 2) Keep the launch date and do it as a follow-up phase I'll hold off on this piece until I hear which you prefer." That last line matters most. Starting "just to be helpful" makes it very hard to charge for later. Four templates (including the "quick favor"): [link] | L27: #freelancetips #clientexperience #smallbusinesstips #solopreneur #consultantlife | N27: Draft
A28: 13 | B28: =IF($C$2="","",$C$2+A28-1) | C28: =IF(B28="","",TEXT(B28,"ddd")) | D28: Month 1: Content | E28: TikTok / Reels / Shorts (+ LinkedIn native) | F28: Short video | G28: C-V13 | H28: AI proposals: the one rule | I28: Never let AI set your prices. | J28: /blog/write-a-proposal-with-ai/ | K28: AI can draft proposals that don't sound generic, but it should never set your prices or promises. Seven-part structure + prompt at the link in bio. | L28: #freelancetips #clientexperience #smallbusinesstips #solopreneur #consultantlife | M28: graphics/video_covers/C-V13.png | N28: Draft
A29: 14 | B29: =IF($C$2="","",$C$2+A29-1) | C29: =IF(B29="","",TEXT(B29,"ddd")) | D29: Month 1: Content | E29: LinkedIn + Instagram | F29: Promotional post | G29: C-P05 | H29: Series: Getting Paid | J29: /category/getting-paid/ | K29: This month's Getting Paid series, all free: → The 5-stage payment reminder schedule → Deposits, milestones and payment terms → What every invoice should include → Tracking invoices in a spreadsheet (tested formulas) Start here: [link] | L29: #freelancebusiness #invoicing #smallbusinessowner #getpaid #solopreneur | M29: graphics/promo_cards/C-P05.png | N29: Draft
A30: 14 | B30: =IF($C$2="","",$C$2+A30-1) | C30: =IF(B30="","",TEXT(B30,"ddd")) | D30: Month 1: Content | E30: TikTok / Reels / Shorts (+ LinkedIn native) | F30: Short video | G30: C-V14 | H30: Starter kit walkthrough | I30: Ten prompts for the admin you do every week, free. | J30: /newsletter/ | K30: The free Client Admin Starter Kit: 10 AI prompts for the admin you do every week + a printable 30-minute weekly review checklist. Link in bio. | L30: #bandofone #solopreneur #freelancer #virtualassistant #consultant | M30: graphics/video_covers/C-V14.png | N30: Draft
A31: 15 | B31: =IF($C$2="","",$C$2+A31-1) | C31: =IF(B31="","",TEXT(B31,"ddd")) | D31: Month 1: Content | E31: Instagram | F31: Educational post (carousel) | G31: C-E08 | H31: What every invoice needs | J31: /blog/what-to-include-on-an-invoice/ | K31: Remove every reason for your invoice to be set aside. Full checklist, plus the UK government's list as an example baseline, at the link in bio. | L31: #freelancebusiness #invoicing #smallbusinessowner #getpaid #solopreneur | M31: graphics/carousels/C-E08_01.png | N31: Draft
A32: 15 | B32: =IF($C$2="","",$C$2+A32-1) | C32: =IF(B32="","",TEXT(B32,"ddd")) | D32: Month 1: Content | E32: TikTok / Reels / Shorts (+ LinkedIn native) | F32: Short video | G32: C-V15 | H32: Invoice details that prevent late payment | I32: Late payments often start with the invoice itself. | J32: /blog/what-to-include-on-an-invoice/ | K32: Remove every reason for your invoice to be set aside: clear description, real due date, easy payment, right recipient. Full checklist (and where to check your country's rules) at the link in bio. | L32: #freelancebusiness #invoicing #smallbusinessowner #getpaid #solopreneur | M32: graphics/video_covers/C-V15.png | N32: Draft
A33: 16 | B33: =IF($C$2="","",$C$2+A33-1) | C33: =IF(B33="","",TEXT(B33,"ddd")) | D33: Month 1: Content | E33: LinkedIn | F33: Promotional post | G33: C-P06 | H33: AI, Done Right series | J33: /category/ai-done-right/ | K33: Using AI for client work without the generic emails or the privacy worries. Four free guides: → Keep client data private (ChatGPT, Claude, Gemini settings) → The one-page AI business brief → Make AI drafts sound like you → 12 client-email prompts with guardrails [link] | L33: #AItools #ChatGPTtips #AIforBusiness #promptengineering #freelancetips | M33: graphics/promo_cards/C-P06.png | N33: Draft
A34: 16 | B34: =IF($C$2="","",$C$2+A34-1) | C34: =IF(B34="","",TEXT(B34,"ddd")) | D34: Month 1: Content | E34: TikTok / Reels / Shorts (+ LinkedIn native) | F34: Short video | G34: C-V16 | H34: SOPs for a one-person business | I34: SOPs aren't just for companies with an operations team. | J34: /blog/sop-template-one-person-business/ | K34: A one-page SOP template for solo businesses, plus the AI prompt that turns rough notes into a finished SOP (and flags gaps instead of inventing steps). Link in bio. | L34: #systemsthinking #SOP #productivitytips #solopreneur #businesssystems | M34: graphics/video_covers/C-V16.png | N34: Draft
A35: 17 | B35: =IF($C$2="","",$C$2+A35-1) | C35: =IF(B35="","",TEXT(B35,"ddd")) | D35: Month 1: Content | E35: LinkedIn | F35: Educational post | G35: C-E09 | H35: Voice profile | J35: /blog/make-ai-sound-like-you/ | K35: "I hope this email finds you well." "I'm thrilled to…" "Please don't hesitate to reach out." Clients can spot AI emails from the first line. A voice profile fixes most of it. Paste 3–5 emails you actually wrote (names removed) and ask the AI to describe: • typical sentence length • greeting and sign-off habits • formality (1–5) • things you never do • how you deliver bad news • 3 "do this / not that" examples Key instruction: "Don't invent traits that aren't in the samples." Prompt + example: [link] | L35: #AItools #ChatGPTtips #AIforBusiness #promptengineering #freelancetips | N35: Draft
A36: 17 | B36: =IF($C$2="","",$C$2+A36-1) | C36: =IF(B36="","",TEXT(B36,"ddd")) | D36: Month 1: Content | E36: TikTok / Reels / Shorts (+ LinkedIn native) | F36: Short video | G36: C-V17 | H36: Make vs Zapier vs n8n in 45 seconds | I36: Make, Zapier or n8n? Here's the honest short version. | J36: /blog/make-vs-zapier-vs-n8n/ | K36: Make vs Zapier vs n8n for freelancers: simplest start, best budget multi-step, most control. Researched from official pricing pages (checked Sept 2026), not hands-on tested. Full comparison at the link in bio. | L36: #nocode #automation #smallbusinesstools #freelancetools #solopreneur | M36: graphics/video_covers/C-V17.png | N36: Draft
A37: 18 | B37: =IF($C$2="","",$C$2+A37-1) | C37: =IF(B37="","",TEXT(B37,"ddd")) | D37: Month 1: Content | E37: TikTok / Reels / Shorts (+ LinkedIn native) | F37: Short video | G37: C-V18 | H37: A prompt that says [NEED INFO] | I37: The most useful words in any AI prompt: 'write NEED INFO instead of guessing'. | J37: /blog/ai-prompts-for-client-emails/ | K37: One line that stops AI inventing details in client emails: "write [NEED INFO] instead of guessing." 12 client-email prompts with guardrails at the link in bio. | L37: #AItools #ChatGPTtips #AIforBusiness #promptengineering #freelancetips | M37: graphics/video_covers/C-V18.png | N37: Draft
A38: 19 | B38: =IF($C$2="","",$C$2+A38-1) | C38: =IF(B38="","",TEXT(B38,"ddd")) | D38: Month 1: Content | E38: Instagram | F38: Educational post (carousel) | G38: C-E10 | H38: The 45-minute weekly admin review | J38: /blog/weekly-admin-review/ | K38: Give admin one appointment a week and it stops leaking into every day. Agenda + an AI prompt that pre-sorts it at the link in bio. | L38: #systemsthinking #SOP #productivitytips #solopreneur #businesssystems | M38: graphics/carousels/C-E10_01.png | N38: Draft
A39: 19 | B39: =IF($C$2="","",$C$2+A39-1) | C39: =IF(B39="","",TEXT(B39,"ddd")) | D39: Month 1: Content | E39: TikTok / Reels / Shorts (+ LinkedIn native) | F39: Short video | G39: C-V19 | H39: Free newsletter tools: what actually differs | I39: If you want a free welcome email sequence, the free plans differ a lot. | J39: /blog/mailerlite-vs-kit-vs-beehiiv/ | K39: MailerLite vs Kit vs beehiiv for a service business newsletter: the free-plan difference that matters is automation. Researched from official pricing pages (Sept 2026). Link in bio. | L39: #nocode #automation #smallbusinesstools #freelancetools #solopreneur | M39: graphics/video_covers/C-V19.png | N39: Draft
A40: 20 | B40: =IF($C$2="","",$C$2+A40-1) | C40: =IF(B40="","",TEXT(B40,"ddd")) | D40: Month 1: Content | E40: Instagram | F40: Promotional post | G40: C-P07 | H40: Save this: prompt guardrails | J40: /blog/ai-prompts-for-client-emails/ | K40: Save this post: 4 guardrail lines for any AI assistant used for client work → never invent prices/dates/facts · write [NEED INFO] instead of guessing · under 200 words · ask one question if unclear. 12 prompts built on them at the link in bio. | L40: #AItools #ChatGPTtips #AIforBusiness #promptengineering #freelancetips | M40: graphics/promo_cards/C-P07.png | N40: Draft
A41: 20 | B41: =IF($C$2="","",$C$2+A41-1) | C41: =IF(B41="","",TEXT(B41,"ddd")) | D41: Month 1: Content | E41: TikTok / Reels / Shorts (+ LinkedIn native) | F41: Short video | G41: C-V20 | H41: The kickoff summary email | I41: The email you send after the kickoff call saves more arguments than any contract clause. | J41: /blog/client-onboarding-checklist/ | K41: The kickoff summary email: same day, five parts, and your written answer to questions that come up in week six. Part of the onboarding checklist at the link in bio. | L41: #freelancetips #clientexperience #smallbusinesstips #solopreneur #consultantlife | M41: graphics/video_covers/C-V20.png | N41: Draft
A42: 21 | B42: =IF($C$2="","",$C$2+A42-1) | C42: =IF(B42="","",TEXT(B42,"ddd")) | D42: Month 1: Content | E42: LinkedIn | F42: Educational post | G42: C-E11 | H42: Deposits and milestones | J42: /blog/deposits-and-payment-terms/ | K42: Payment problems are usually decided before the project starts. Three decisions to make once and put in every proposal: 1. Deposit: "Work starts once the deposit has cleared." (Then stick to it.) 2. Milestones clients can see: "design approved", not "50% complete" 3. Terms with a real date on every invoice: "Due 14 October", not just "Net 14" Why: in Bonsai's data, invoices over $20,000 were 3× more likely to be late than invoices under $100. Smaller, earlier payments mean less at risk at any moment. Wording + a full example (general info, not legal advice): [link] | L42: #freelancebusiness #invoicing #smallbusinessowner #getpaid #solopreneur | N42: Draft
A43: 21 | B43: =IF($C$2="","",$C$2+A43-1) | C43: =IF(B43="","",TEXT(B43,"ddd")) | D43: Month 1: Content | E43: TikTok / Reels / Shorts (+ LinkedIn native) | F43: Short video | G43: C-V21 | H43: Tested vs researched: why we label | I43: When you read a tool review, ask one question: did they actually use it? | J43: /editorial-policy/ | K43: Did the reviewer actually use the tool? Our tool articles are always labeled Tested or Researched, with dates. Why we do it: editorial policy at the link in bio. | L43: #bandofone #solopreneur #freelancer #virtualassistant #consultant | M43: graphics/video_covers/C-V21.png | N43: Draft
A44: 22 | B44: =IF($C$2="","",$C$2+A44-1) | C44: =IF(B44="","",TEXT(B44,"ddd")) | D44: Month 1: Content | E44: LinkedIn + Instagram | F44: Promotional post | G44: C-P08 | H44: Honest tool comparisons | J44: /category/tools-honestly/ | K44: Tools, Honestly: researched comparisons for solo service businesses, with free-plan limits checked on official pricing pages (Sept 2026): → Make vs Zapier vs n8n → MailerLite vs Kit vs beehiiv → Tally vs Google Forms vs Jotform → Spreadsheet vs Notion vs CRM No affiliate links. [link] | L44: #nocode #automation #smallbusinesstools #freelancetools #solopreneur | M44: graphics/promo_cards/C-P08.png | N44: Draft
A45: 22 | B45: =IF($C$2="","",$C$2+A45-1) | C45: =IF(B45="","",TEXT(B45,"ddd")) | D45: Month 1: Content | E45: TikTok / Reels / Shorts (+ LinkedIn native) | F45: Short video | G45: C-V22 | H45: One tool per job | I45: Two tools for the same job is worse than one simple one. | J45: /blog/minimum-tool-stack/ | K45: The minimum tool stack for a solo service business: eight jobs, one tool each, mostly free to start (free-plan limits checked on official pricing pages). Link in bio. | L45: #systemsthinking #SOP #productivitytips #solopreneur #businesssystems | M45: graphics/video_covers/C-V22.png | N45: Draft
A46: 23 | B46: =IF($C$2="","",$C$2+A46-1) | C46: =IF(B46="","",TEXT(B46,"ddd")) | D46: Month 1: Content | E46: Instagram | F46: Educational post (carousel) | G46: C-E12 | H46: SOP template for solo businesses | J46: /blog/sop-template-one-person-business/ | K46: SOPs aren't just for teams. When you work alone, you're the one who has to remember everything. Template + AI prompt at the link in bio. | L46: #systemsthinking #SOP #productivitytips #solopreneur #businesssystems | M46: graphics/carousels/C-E12_01.png | N46: Draft
A47: 23 | B47: =IF($C$2="","",$C$2+A47-1) | C47: =IF(B47="","",TEXT(B47,"ddd")) | D47: Month 1: Content | E47: TikTok / Reels / Shorts (+ LinkedIn native) | F47: Short video | G47: C-V23 | H47: Stage D: ask for a date | I47: Fourteen days late? Stop asking 'when'. Ask for a date. | J47: /blog/payment-reminder-schedule/ | K47: At 14 days overdue, the key move is getting a payment date in writing. The exact wording (and the other four stages) at the link in bio. | L47: #freelancebusiness #invoicing #smallbusinessowner #getpaid #solopreneur | M47: graphics/video_covers/C-V23.png | N47: Draft
A48: 24 | B48: =IF($C$2="","",$C$2+A48-1) | C48: =IF(B48="","",TEXT(B48,"ddd")) | D48: Month 1: Content | E48: TikTok / Reels / Shorts (+ LinkedIn native) | F48: Short video | G48: C-V24 | H48: Intake forms: keep it to 7 fields | I48: Every extra required field on your inquiry form is a reason not to submit. | J48: /blog/client-intake-form-tools/ | K48: Your inquiry form needs 7 fields or fewer. The questions to ask (and a researched comparison of Tally, Google Forms and Jotform) at the link in bio. | L48: #nocode #automation #smallbusinesstools #freelancetools #solopreneur | M48: graphics/video_covers/C-V24.png | N48: Draft
A49: 25 | B49: =IF($C$2="","",$C$2+A49-1) | C49: =IF(B49="","",TEXT(B49,"ddd")) | D49: Month 1: Content | E49: LinkedIn | F49: Educational post | G49: C-E13 | H49: Guardrail lines for AI prompts | J49: /blog/ai-prompts-for-client-emails/ | K49: Four lines I'd add to every AI assistant used for client work: 1. "Never invent prices, dates or facts about clients." 2. "If information is missing, write [NEED INFO] instead of guessing." 3. "Keep client emails under 200 words unless I ask otherwise." 4. "If my request is ambiguous, ask one clarifying question." Save them as custom instructions and they apply to every chat. AI drafts, you decide. 12 client-email prompts built this way: [link] | L49: #AItools #ChatGPTtips #AIforBusiness #promptengineering #freelancetips | N49: Draft
A50: 25 | B50: =IF($C$2="","",$C$2+A50-1) | C50: =IF(B50="","",TEXT(B50,"ddd")) | D50: Month 1: Content | E50: TikTok / Reels / Shorts (+ LinkedIn native) | F50: Short video | G50: C-V25 | H50: Temporary chats and privacy settings | I50: Turning off AI training is a good default. It doesn't mean nothing is stored. | J50: /blog/client-data-privacy-ai/ | K50: AI privacy settings are worth setting, but 'training off' isn't 'nothing stored'. What ChatGPT, Claude and Gemini's help pages say (checked Sept 2026), and why redaction comes first. Link in bio. | L50: #AItools #ChatGPTtips #AIforBusiness #promptengineering #freelancetips | M50: graphics/video_covers/C-V25.png | N50: Draft
A51: 26 | B51: =IF($C$2="","",$C$2+A51-1) | C51: =IF(B51="","",TEXT(B51,"ddd")) | D51: Month 1: Content | E51: LinkedIn | F51: Promotional post | G51: C-P09 | H51: Ask me anything: admin systems | J51: /contact/ | K51: What's the one admin task that eats most of your week as a solo business owner? Reply in the comments. I'll turn the most common answers into next month's articles and templates (free). | L51: #bandofone #solopreneur #freelancer #virtualassistant #consultant | M51: graphics/promo_cards/C-P09.png | N51: Draft
A52: 26 | B52: =IF($C$2="","",$C$2+A52-1) | C52: =IF(B52="","",TEXT(B52,"ddd")) | D52: Month 1: Content | E52: TikTok / Reels / Shorts (+ LinkedIn native) | F52: Short video | G52: C-V26 | H52: Spreadsheet, Notion or CRM? | I52: Where should a solo business track clients? The one that you'll open every week. | J52: /blog/spreadsheet-vs-notion-vs-crm/ | K52: Spreadsheet, Notion or CRM for tracking clients? The honest trade-offs, and the one habit that matters more than the tool. Link in bio. | L52: #nocode #automation #smallbusinesstools #freelancetools #solopreneur | M52: graphics/video_covers/C-V26.png | N52: Draft
A53: 27 | B53: =IF($C$2="","",$C$2+A53-1) | C53: =IF(B53="","",TEXT(B53,"ddd")) | D53: Month 1: Content | E53: Instagram | F53: Educational post (carousel) | G53: C-E14 | H53: Inquiry form: 7 fields | J53: /blog/client-intake-form-tools/ | K53: Every extra required field is a reason not to submit. The questions to ask, plus a researched comparison of Tally, Google Forms and Jotform, at the link in bio. | L53: #nocode #automation #smallbusinesstools #freelancetools #solopreneur | M53: graphics/carousels/C-E14_01.png | N53: Draft
A54: 27 | B54: =IF($C$2="","",$C$2+A54-1) | C54: =IF(B54="","",TEXT(B54,"ddd")) | D54: Month 1: Content | E54: TikTok / Reels / Shorts (+ LinkedIn native) | F54: Short video | G54: C-V27 | H54: How to report a delay | I54: How to tell a client about a delay without a wall of apologies. | J54: /blog/weekly-client-update-template/ | K54: Delays happen. Here's how to report one: state it, one line of why, the new date, and a choice if there is one. More in the weekly client update guide (link in bio). | L54: #freelancetips #clientexperience #smallbusinesstips #solopreneur #consultantlife | M54: graphics/video_covers/C-V27.png | N54: Draft
A55: 28 | B55: =IF($C$2="","",$C$2+A55-1) | C55: =IF(B55="","",TEXT(B55,"ddd")) | D55: Month 1: Content | E55: TikTok / Reels / Shorts (+ LinkedIn native) | F55: Short video | G55: C-V28 | H55: Testimonial request that asks permission | I55: The right way to ask for a testimonial, and the one thing never to do. | J55: /blog/ai-prompts-for-client-emails/ | K55: Ask for testimonials the right way: three optional questions, clear permission, client approves the final wording. Never write one for them. Prompt at the link in bio. | L55: #AItools #ChatGPTtips #AIforBusiness #promptengineering #freelancetips | M55: graphics/video_covers/C-V28.png | N55: Draft
A56: 29 | B56: =IF($C$2="","",$C$2+A56-1) | C56: =IF(B56="","",TEXT(B56,"ddd")) | D56: Month 1: Content | E56: LinkedIn | F56: Educational post | G56: C-E15 | H56: Four numbers to track | J56: /blog/weekly-admin-review/ | K56: You don't need a dashboard to know if your admin system works. Four numbers, once a month: 1. Hours on admin (a rough estimate is fine) 2. Overdue invoices (count and total) 3. Average time to first reply on new inquiries 4. Proposals sent vs accepted Watch them for 2–3 months. Measure, don't assume, including anything we tell you. The weekly review that feeds them: [link] | L56: #systemsthinking #SOP #productivitytips #solopreneur #businesssystems | N56: Draft
A57: 29 | B57: =IF($C$2="","",$C$2+A57-1) | C57: =IF(B57="","",TEXT(B57,"ddd")) | D57: Month 1: Content | E57: TikTok / Reels / Shorts (+ LinkedIn native) | F57: Short video | G57: C-V29 | H57: Track four numbers | I57: You don't need a dashboard. You need four numbers once a month. | J57: /blog/weekly-admin-review/ | K57: Four numbers, once a month: admin hours, overdue invoices, time to first reply, proposals sent vs accepted. Measure your system; don't take anyone's word for it. Link in bio. | L57: #systemsthinking #SOP #productivitytips #solopreneur #businesssystems | M57: graphics/video_covers/C-V29.png | N57: Draft
A58: 30 | B58: =IF($C$2="","",$C$2+A58-1) | C58: =IF(B58="","",TEXT(B58,"ddd")) | D58: Month 1: Content | E58: LinkedIn + Instagram | F58: Promotional post | G58: C-P10 | H58: Month recap + starter kit | J58: /newsletter/ | K58: 30 days, 20 free guides for the admin side of a one-person business: onboarding, proposals, weekly updates, getting paid, AI privacy, SOPs and honest tool comparisons. If you only take one thing: book a 45-minute weekly admin review, starting this week. Free starter kit (10 prompts + checklist): [link] | L58: #bandofone #solopreneur #freelancer #virtualassistant #consultant | M58: graphics/promo_cards/C-P10.png | N58: Draft
A59: 30 | B59: =IF($C$2="","",$C$2+A59-1) | C59: =IF(B59="","",TEXT(B59,"ddd")) | D59: Month 1: Content | E59: TikTok / Reels / Shorts (+ LinkedIn native) | F59: Short video | G59: C-V30 | H59: Month recap + where to start | I59: Thirty days of admin systems. If you only do one thing, do this. | J59: /newsletter/ | K59: 30 days of admin systems for businesses of one. If you only do one thing: book a 45-minute weekly admin review. Everything from this month + the free starter kit at the link in bio. | L59: #bandofone #solopreneur #freelancer #virtualassistant #consultant | M59: graphics/video_covers/C-V30.png | N59: Draft
A60: 31 | B60: =IF($C$2="","",$C$2+A60-1) | C60: =IF(B60="","",TEXT(B60,"ddd")) | D60: Month 2: Product launch | E60: LinkedIn | F60: Educational post | G60: P-E01 | H60: Why prompt packs disappoint | K60: Why do big prompt packs disappoint? Because a one-line prompt can't know: → what you're asking it to do (objective) → when it applies (use case) → what you'll paste in (inputs) → what "good" looks like (output format) → what it must never do (guardrails) A useful prompt specifies all five. It's longer, but you use it again and again. I'm launching a 100-prompt library built this way next week. Here's one of them for free, the business brief builder: [link to starter kit] | L60: #AItools #ChatGPTtips #AIforBusiness #promptengineering #freelancetips | N60: Draft
A61: 31 | B61: =IF($C$2="","",$C$2+A61-1) | C61: =IF(B61="","",TEXT(B61,"ddd")) | D61: Month 2: Product launch | E61: TikTok / Reels / Shorts (+ LinkedIn native) | F61: Short video | G61: P-V01 | H61: Behind the build: why a system, not a prompt pack | I61: I could have made a 10,000-prompt pack. Here's why I didn't. | J61: /bundle/ | K61: Why the Band of One products are a system, not a 10,000-prompt pack. Launching next week. I'll show you what's inside every day until then. | L61: #bandofone #solopreneur #freelancer #virtualassistant #consultant | M61: graphics/video_covers/P-V01.png | N61: Draft
A62: 32 | B62: =IF($C$2="","",$C$2+A62-1) | C62: =IF(B62="","",TEXT(B62,"ddd")) | D62: Month 2: Product launch | E62: Instagram | F62: Educational post (carousel) | G62: P-E02 | H62: Anatomy of a prompt card | K62: Every prompt in The Band of One Prompt Library follows this format. The library launches next week; 10 prompts are free in the starter kit now (link in bio). | L62: #AItools #ChatGPTtips #AIforBusiness #promptengineering #freelancetips | M62: graphics/carousels/P-E02_01.png | N62: Draft
A63: 32 | B63: =IF($C$2="","",$C$2+A63-1) | C63: =IF(B63="","",TEXT(B63,"ddd")) | D63: Month 2: Product launch | E63: TikTok / Reels / Shorts (+ LinkedIn native) | F63: Short video | G63: P-V02 | H63: The Client Desk dashboard tour | I63: This is what my Monday morning admin check looks like: one screen. | J63: /bundle/ | K63: A tour of The Client Desk dashboard (fictional sample data): next actions, invoices needing a reminder, pipeline, weekly numbers. Excel + Google Sheets, no macros. Launching next week. | L63: #freelancebusiness #invoicing #smallbusinessowner #getpaid #solopreneur | M63: graphics/video_covers/P-V02.png | N63: Draft
A64: 33 | B64: =IF($C$2="","",$C$2+A64-1) | C64: =IF(B64="","",TEXT(B64,"ddd")) | D64: Month 2: Product launch | E64: LinkedIn | F64: Educational post | G64: P-E03 | H64: The one-screen admin check | K64: A solo business needs one screen that answers: 1. Who needs a follow-up this week? 2. Which invoices need a reminder, and which one? 3. What's in the pipeline, by stage? 4. How did this week go? You can build this in any spreadsheet with a few formulas (our free invoice tracker shows how). The Client Desk, launching next week, has it built and tested: a Dashboard tab calculated from your client, project and invoice tabs. It works in Excel and Google Sheets, with no macros. | L64: #freelancebusiness #invoicing #smallbusinessowner #getpaid #solopreneur | N64: Draft
A65: 33 | B65: =IF($C$2="","",$C$2+A65-1) | C65: =IF(B65="","",TEXT(B65,"ddd")) | D65: Month 2: Product launch | E65: TikTok / Reels / Shorts (+ LinkedIn native) | F65: Short video | G65: P-V03 | H65: Anatomy of one prompt card | I65: Here's what a fully specified AI prompt looks like. | J65: /bundle/ | K65: Anatomy of a prompt card from The Band of One Prompt Library: objective, when to use, inputs, guardrails, output format. That's one of 100. Launching next week. | L65: #AItools #ChatGPTtips #AIforBusiness #promptengineering #freelancetips | M65: graphics/video_covers/P-V03.png | N65: Draft
A66: 34 | B66: =IF($C$2="","",$C$2+A66-1) | C66: =IF(B66="","",TEXT(B66,"ddd")) | D66: Month 2: Product launch | E66: Instagram | F66: Educational post (carousel) | G66: P-E04 | H66: The admin audit in 5 steps | K66: This is Chapter 2 of The Solo Admin Playbook. You can do it on paper today for free. | L66: #systemsthinking #SOP #productivitytips #solopreneur #businesssystems | M66: graphics/carousels/P-E04_01.png | N66: Draft
A67: 34 | B67: =IF($C$2="","",$C$2+A67-1) | C67: =IF(B67="","",TEXT(B67,"ddd")) | D67: Month 2: Product launch | E67: TikTok / Reels / Shorts (+ LinkedIn native) | F67: Short video | G67: P-V04 | H67: The admin audit worksheet | I67: Before you fix your admin, find out where the time actually goes. | J67: /blog/what-to-automate-first/ | K67: The admin audit from Chapter 2 of The Solo Admin Playbook. Score your tasks and fix the biggest one first. You can do it for free today; the formula's in the video. | L67: #systemsthinking #SOP #productivitytips #solopreneur #businesssystems | M67: graphics/video_covers/P-V04.png | N67: Draft
A68: 35 | B68: =IF($C$2="","",$C$2+A68-1) | C68: =IF(B68="","",TEXT(B68,"ddd")) | D68: Month 2: Product launch | E68: TikTok / Reels / Shorts (+ LinkedIn native) | F68: Short video | G68: P-V05 | H68: Reminder stages in the spreadsheet | I68: My spreadsheet tells me which payment reminder to send. Here's how. | J68: /bundle/ | K68: How The Client Desk works out which payment reminder is due (A–E) and whether you've sent it. Formulas tested before release; timing adjustable in Settings. Launching next week. | L68: #freelancebusiness #invoicing #smallbusinessowner #getpaid #solopreneur | M68: graphics/video_covers/P-V05.png | N68: Draft
A69: 36 | B69: =IF($C$2="","",$C$2+A69-1) | C69: =IF(B69="","",TEXT(B69,"ddd")) | D69: Month 2: Product launch | E69: LinkedIn | F69: Educational post | G69: P-E05 | H69: Five decisions for every admin task | K69: Every recurring admin task gets one of five decisions: ELIMINATE: nobody would notice if you stopped TEMPLATE: it's nearly identical every time AI DRAFT: the structure repeats, the content changes AUTOMATE: rule-based, frequent, low-risk and already templated KEEP HUMAN: high risk, high judgment or relationship-critical Notice automation comes after templating. If you can't write it as a checklist, you're not ready to automate it. (From The Solo Admin Playbook, Chapter 2.) | L69: #systemsthinking #SOP #productivitytips #solopreneur #businesssystems | N69: Draft
A70: 36 | B70: =IF($C$2="","",$C$2+A70-1) | C70: =IF(B70="","",TEXT(B70,"ddd")) | D70: Month 2: Product launch | E70: TikTok / Reels / Shorts (+ LinkedIn native) | F70: Short video | G70: P-V06 | H70: 3 free prompts from the library | I70: Three prompts from the library you can use today, free. | J70: /newsletter/ | K70: Three prompts from The Band of One Prompt Library you can use free today: business brief builder, new-inquiry reply, call notes → summary. All in the free starter kit (link in bio). | L70: #AItools #ChatGPTtips #AIforBusiness #promptengineering #freelancetips | M70: graphics/video_covers/P-V06.png | N70: Draft
A71: 37 | B71: =IF($C$2="","",$C$2+A71-1) | C71: =IF(B71="","",TEXT(B71,"ddd")) | D71: Month 2: Product launch | E71: LinkedIn + Instagram | F71: Promotional post | G71: P-P01 | H71: Launching tomorrow | K71: Tomorrow: the Band of One products go on sale. • The Solo Admin Playbook: $24 • The Client Desk: $29 • The Band of One Prompt Library: $19 • All three (Complete Bundle): $49 Launch code FOUNDING takes $10 off the bundle ($5 off the playbook or desk, $4 off the library) until [LAUNCH END DATE]. 14-day refund policy. | L71: #bandofone #solopreneur #freelancer #virtualassistant #consultant | M71: graphics/promo_cards/P-P01.png | N71: Draft
A72: 37 | B72: =IF($C$2="","",$C$2+A72-1) | C72: =IF(B72="","",TEXT(B72,"ddd")) | D72: Month 2: Product launch | E72: TikTok / Reels / Shorts (+ LinkedIn native) | F72: Short video | G72: P-V07 | H72: Launch tomorrow: what, price, how | I72: Tomorrow the Band of One products go on sale. Here's exactly what they cost. | J72: /bundle/ | K72: Launching tomorrow: The Solo Admin Playbook ($24), The Client Desk ($29), The Prompt Library ($19) or all three for $49. Code FOUNDING until [LAUNCH END DATE]. 14-day refund policy. | L72: #bandofone #solopreneur #freelancer #virtualassistant #consultant | M72: graphics/video_covers/P-V07.png | N72: Draft
A73: 38 | B73: =IF($C$2="","",$C$2+A73-1) | C73: =IF(B73="","",TEXT(B73,"ddd")) | D73: Month 2: Product launch | E73: LinkedIn + Instagram | F73: Promotional post | G73: P-P02 | H73: It's live | K73: It's live. The Band of One Complete Bundle: the playbook (how), The Client Desk (where) and 100 prompts (what to say), built as one admin system for a business of one. $49 ($72 separately). Code FOUNDING until [LAUNCH END DATE]. 14-day refund policy. [STORE LINK] | L73: #bandofone #solopreneur #freelancer #virtualassistant #consultant | M73: graphics/promo_cards/P-P02.png | N73: Draft
A74: 38 | B74: =IF($C$2="","",$C$2+A74-1) | C74: =IF(B74="","",TEXT(B74,"ddd")) | D74: Month 2: Product launch | E74: TikTok / Reels / Shorts (+ LinkedIn native) | F74: Short video | G74: P-V08 | H74: It's live | I74: The Band of One bundle is live. | J74: /bundle/ | K74: It's live: The Band of One Complete Bundle, with the playbook, The Client Desk workbook and the 100-prompt library, built to work together. Code FOUNDING until [LAUNCH END DATE]. | L74: #bandofone #solopreneur #freelancer #virtualassistant #consultant | M74: graphics/video_covers/P-V08.png | N74: Draft
A75: 39 | B75: =IF($C$2="","",$C$2+A75-1) | C75: =IF(B75="","",TEXT(B75,"ddd")) | D75: Month 2: Product launch | E75: Instagram | F75: Educational post (carousel) | G75: P-E06 | H75: What AI is good and bad at (client work) | K75: From Chapter 3 of The Solo Admin Playbook: using AI safely with client work. | L75: #systemsthinking #SOP #productivitytips #solopreneur #businesssystems | M75: graphics/carousels/P-E06_01.png | N75: Draft
A76: 39 | B76: =IF($C$2="","",$C$2+A76-1) | C76: =IF(B76="","",TEXT(B76,"ddd")) | D76: Month 2: Product launch | E76: TikTok / Reels / Shorts (+ LinkedIn native) | F76: Short video | G76: P-V09 | H76: Inside the playbook in 45 seconds | I76: Thirty-eight pages, flipped through in forty-five seconds. | J76: /bundle/ | K76: The Solo Admin Playbook in 45 seconds: admin audit, safe AI setup, six client workflows with templates and prompts, SOPs and the weekly review. PDF + editable DOCX. | L76: #systemsthinking #SOP #productivitytips #solopreneur #businesssystems | M76: graphics/video_covers/P-V09.png | N76: Draft
A77: 40 | B77: =IF($C$2="","",$C$2+A77-1) | C77: =IF(B77="","",TEXT(B77,"ddd")) | D77: Month 2: Product launch | E77: Instagram | F77: Promotional post | G77: P-P03 | H77: Prompt Library spotlight | K77: 100 prompts, each doing one job: objective, inputs, guardrails, output format. PDF + searchable spreadsheet + Notion-ready CSV. $19 (code FOUNDING until [LAUNCH END DATE]). Link in bio. | L77: #AItools #ChatGPTtips #AIforBusiness #promptengineering #freelancetips | M77: graphics/promo_cards/P-P03.png | N77: Draft
A78: 40 | B78: =IF($C$2="","",$C$2+A78-1) | C78: =IF(B78="","",TEXT(B78,"ddd")) | D78: Month 2: Product launch | E78: TikTok / Reels / Shorts (+ LinkedIn native) | F78: Short video | G78: P-V10 | H78: Search the library by keyword | I78: I typed 'scope' and found the right prompt in two seconds. | J78: /bundle/ | K78: The Prompt Library's spreadsheet version has a Search tab: type 'scope', 'invoice' or 'delay' and get the matching prompts. Plus favorites, notes and a Notion-ready CSV. | L78: #AItools #ChatGPTtips #AIforBusiness #promptengineering #freelancetips | M78: graphics/video_covers/P-V10.png | N78: Draft
A79: 41 | B79: =IF($C$2="","",$C$2+A79-1) | C79: =IF(B79="","",TEXT(B79,"ddd")) | D79: Month 2: Product launch | E79: LinkedIn | F79: Educational post | G79: P-E07 | H79: Prompt: responding to a discount request | K79: "Can you do it cheaper?" A prompt for replying without an apology spiral: "A client asked for a lower price: [REQUEST]. Draft a reply that acknowledges their budget, restates the value tied to their goals, and offers these options only: [MY OPTIONS]. If I've chosen not to reduce the price, say so kindly and clearly. Under 150 words, confident, no apology spiral, in my voice [VOICE PROFILE]." You decide the options (smaller scope? phased start?). The AI only handles the wording. (HARD-01, from the Tough Conversations section of The Band of One Prompt Library.) | L79: #AItools #ChatGPTtips #AIforBusiness #promptengineering #freelancetips | N79: Draft
A80: 41 | B80: =IF($C$2="","",$C$2+A80-1) | C80: =IF(B80="","",TEXT(B80,"ddd")) | D80: Month 2: Product launch | E80: TikTok / Reels / Shorts (+ LinkedIn native) | F80: Short video | G80: P-V11 | H80: Setting up The Client Desk in 10 minutes | I80: From download to your first client in about ten minutes. | J80: /bundle/ | K80: Setting up The Client Desk: open, fill in Settings, clear the sample rows, add a client. About ten minutes, and there's a 13-page user guide if you get stuck. | L80: #freelancebusiness #invoicing #smallbusinessowner #getpaid #solopreneur | M80: graphics/video_covers/P-V11.png | N80: Draft
A81: 42 | B81: =IF($C$2="","",$C$2+A81-1) | C81: =IF(B81="","",TEXT(B81,"ddd")) | D81: Month 2: Product launch | E81: LinkedIn | F81: Promotional post | G81: P-P04 | H81: Client Desk spotlight | K81: The Client Desk: one spreadsheet for clients, projects, invoices and payment reminders, with a dashboard of what needs attention this week. ✓ Excel, Google Sheets, LibreOffice (no macros) ✓ Reminder stages A–E calculated for every invoice ✓ Formulas tested before release ✓ Sample business + 13-page guide $29 (code FOUNDING until [LAUNCH END DATE]). [STORE LINK] | L81: #freelancebusiness #invoicing #smallbusinessowner #getpaid #solopreneur | M81: graphics/promo_cards/P-P04.png | N81: Draft
A82: 42 | B82: =IF($C$2="","",$C$2+A82-1) | C82: =IF(B82="","",TEXT(B82,"ddd")) | D82: Month 2: Product launch | E82: TikTok / Reels / Shorts (+ LinkedIn native) | F82: Short video | G82: P-V12 | H82: Prompt demo: discount request | I82: A client asks, 'Can you do it cheaper?' Here's the prompt I use. | J82: /bundle/ | K82: 'Can you do it cheaper?' Prompt HARD-01 drafts a confident reply that offers only the options you choose. From the Tough Conversations section of The Band of One Prompt Library. | L82: #AItools #ChatGPTtips #AIforBusiness #promptengineering #freelancetips | M82: graphics/video_covers/P-V12.png | N82: Draft
A83: 43 | B83: =IF($C$2="","",$C$2+A83-1) | C83: =IF(B83="","",TEXT(B83,"ddd")) | D83: Month 2: Product launch | E83: Instagram | F83: Educational post (carousel) | G83: P-E08 | H83: One system, three tools | K83: Designed as one system. Buy one or all three. Details at the link in bio. | L83: #bandofone #solopreneur #freelancer #virtualassistant #consultant | M83: graphics/carousels/P-E08_01.png | N83: Draft
A84: 43 | B84: =IF($C$2="","",$C$2+A84-1) | C84: =IF(B84="","",TEXT(B84,"ddd")) | D84: Month 2: Product launch | E84: TikTok / Reels / Shorts (+ LinkedIn native) | F84: Short video | G84: P-V13 | H84: How the three connect | I84: Why these three products share the same IDs. | J84: /bundle/ | K84: The playbook, The Client Desk and the Prompt Library share prompt IDs, reminder stages and the weekly review. One system, not three random downloads. | L84: #bandofone #solopreneur #freelancer #virtualassistant #consultant | M84: graphics/video_covers/P-V13.png | N84: Draft
A85: 44 | B85: =IF($C$2="","",$C$2+A85-1) | C85: =IF(B85="","",TEXT(B85,"ddd")) | D85: Month 2: Product launch | E85: Instagram | F85: Promotional post | G85: P-P05 | H85: Playbook spotlight | K85: The Solo Admin Playbook: 38 pages, 6 client workflows, worksheets, templates and 17 prompts. PDF + editable DOCX. $24 (code FOUNDING until [LAUNCH END DATE]). Link in bio. | L85: #systemsthinking #SOP #productivitytips #solopreneur #businesssystems | M85: graphics/promo_cards/P-P05.png | N85: Draft
A86: 44 | B86: =IF($C$2="","",$C$2+A86-1) | C86: =IF(B86="","",TEXT(B86,"ddd")) | D86: Month 2: Product launch | E86: TikTok / Reels / Shorts (+ LinkedIn native) | F86: Short video | G86: P-V14 | H86: Safe AI setup chapter | I86: The chapter I'd make every freelancer read before using AI with clients. | J86: /bundle/ | K86: Chapter 3 of The Solo Admin Playbook: using AI safely with client work. What it's good and bad at, the redaction habit, and the settings to check. AI drafts; you decide. | L86: #AItools #ChatGPTtips #AIforBusiness #promptengineering #freelancetips | M86: graphics/video_covers/P-V14.png | N86: Draft
A87: 45 | B87: =IF($C$2="","",$C$2+A87-1) | C87: =IF(B87="","",TEXT(B87,"ddd")) | D87: Month 2: Product launch | E87: LinkedIn | F87: Educational post | G87: P-E09 | H87: Reminder stages you can steal | K87: The payment reminder stages built into The Client Desk (and free to steal): A: 3 days before due: heads-up B: due date: reminder C: +7: "anything holding it up?" D: +14: ask for a payment date in writing E: +30: final notice (only consequences in your agreement) The spreadsheet works out which stage each invoice is at and whether you've sent it. You can change the timing in Settings. Templates for every stage are free on the blog: [link] | L87: #freelancebusiness #invoicing #smallbusinessowner #getpaid #solopreneur | N87: Draft
A88: 45 | B88: =IF($C$2="","",$C$2+A88-1) | C88: =IF(B88="","",TEXT(B88,"ddd")) | D88: Month 2: Product launch | E88: TikTok / Reels / Shorts (+ LinkedIn native) | F88: Short video | G88: P-V15 | H88: Admin Audit tab | I88: The spreadsheet ranks your admin tasks for you. | J88: /bundle/ | K88: The Admin Audit tab in The Client Desk scores and ranks your recurring admin tasks, then you choose: eliminate, template, AI draft, automate or keep human. | L88: #systemsthinking #SOP #productivitytips #solopreneur #businesssystems | M88: graphics/video_covers/P-V15.png | N88: Draft
A89: 46 | B89: =IF($C$2="","",$C$2+A89-1) | C89: =IF(B89="","",TEXT(B89,"ddd")) | D89: Month 2: Product launch | E89: LinkedIn + Instagram | F89: Promotional post | G89: P-P06 | H89: Who it's for / not for | K89: The Band of One bundle IS for you if you run a one-person service business and handle your own inquiries, proposals and invoices. It's NOT for you if you need a multi-user CRM, legal or tax advice, or prompts for images and code. Honest fit beats a refund. Details: [STORE LINK] | L89: #bandofone #solopreneur #freelancer #virtualassistant #consultant | M89: graphics/promo_cards/P-P06.png | N89: Draft
A90: 46 | B90: =IF($C$2="","",$C$2+A90-1) | C90: =IF(B90="","",TEXT(B90,"ddd")) | D90: Month 2: Product launch | E90: TikTok / Reels / Shorts (+ LinkedIn native) | F90: Short video | G90: P-V16 | H90: Who it's NOT for | I90: Who shouldn't buy this. | J90: /bundle/ | K90: Who the Band of One bundle is NOT for: teams needing a full CRM, anyone after legal/tax advice, or people looking for image/code prompts. Who it IS for: solo service businesses that want one simple admin system. | L90: #bandofone #solopreneur #freelancer #virtualassistant #consultant | M90: graphics/video_covers/P-V16.png | N90: Draft
A91: 47 | B91: =IF($C$2="","",$C$2+A91-1) | C91: =IF(B91="","",TEXT(B91,"ddd")) | D91: Month 2: Product launch | E91: Instagram | F91: Educational post (carousel) | G91: P-E10 | H91: The delay email, structured | K91: The structure behind prompt DEL-02 in The Band of One Prompt Library. | L91: #AItools #ChatGPTtips #AIforBusiness #promptengineering #freelancetips | M91: graphics/carousels/P-E10_01.png | N91: Draft
A92: 47 | B92: =IF($C$2="","",$C$2+A92-1) | C92: =IF(B92="","",TEXT(B92,"ddd")) | D92: Month 2: Product launch | E92: TikTok / Reels / Shorts (+ LinkedIn native) | F92: Short video | G92: P-V17 | H92: Prompt demo: delay notification | I92: The hardest client email to write, drafted in thirty seconds. | J92: /bundle/ | K92: Prompt DEL-02 drafts the hardest client email (the delay) with the news first, one line of context, the plan and the impact. From The Band of One Prompt Library. You still read it before sending. | L92: #AItools #ChatGPTtips #AIforBusiness #promptengineering #freelancetips | M92: graphics/video_covers/P-V17.png | N92: Draft
A93: 48 | B93: =IF($C$2="","",$C$2+A93-1) | C93: =IF(B93="","",TEXT(B93,"ddd")) | D93: Month 2: Product launch | E93: TikTok / Reels / Shorts (+ LinkedIn native) | F93: Short video | G93: P-V18 | H93: Your next seven days | I93: The last chapter of the playbook is a seven-day plan. Here it is. | J93: /bundle/ | K93: The Solo Admin Playbook ends with a 7-day plan: one small step a day, from the admin audit to your first weekly review. | L93: #systemsthinking #SOP #productivitytips #solopreneur #businesssystems | M93: graphics/video_covers/P-V18.png | N93: Draft
A94: 49 | B94: =IF($C$2="","",$C$2+A94-1) | C94: =IF(B94="","",TEXT(B94,"ddd")) | D94: Month 2: Product launch | E94: LinkedIn | F94: Educational post | G94: P-E11 | H94: 7 days to an admin system | K94: A 7-day plan for an admin system (from the last chapter of The Solo Admin Playbook): Day 1: Admin audit → your top three tasks to fix Day 2: Privacy settings, business brief, voice profile Day 3: Onboarding checklist + welcome email Day 4: Weekly update template + meeting-summary prompt Day 5: Payment terms + reminder templates Day 6: Inquiry reply + proposal structure Day 7: First SOP + first weekly review One step a day. You can start today with just a spreadsheet and a free AI plan. | L94: #systemsthinking #SOP #productivitytips #solopreneur #businesssystems | N94: Draft
A95: 49 | B95: =IF($C$2="","",$C$2+A95-1) | C95: =IF(B95="","",TEXT(B95,"ddd")) | D95: Month 2: Product launch | E95: LinkedIn + Instagram | F95: Promotional post | G95: P-P07 | H95: FAQ post | K95: Before you buy: Does The Client Desk work in Google Sheets? Yes. Do I need a paid AI plan? No, free tiers work. Is it legal or tax advice? No, it's communication templates and systems. What if it isn't useful? Email within 14 days for a full refund. Launch price until [LAUNCH END DATE]. [STORE LINK] | L95: #bandofone #solopreneur #freelancer #virtualassistant #consultant | M95: graphics/promo_cards/P-P07.png | N95: Draft
A96: 49 | B96: =IF($C$2="","",$C$2+A96-1) | C96: =IF(B96="","",TEXT(B96,"ddd")) | D96: Month 2: Product launch | E96: TikTok / Reels / Shorts (+ LinkedIn native) | F96: Short video | G96: P-V19 | H96: FAQ: Google Sheets, AI plans, refunds | I96: The three questions people ask before buying. | J96: /bundle/ | K96: Pre-purchase FAQ: The Client Desk works in Google Sheets and Excel; the prompts work in free AI plans; 14-day refund if it isn't useful. Launch price until [LAUNCH END DATE]. | L96: #bandofone #solopreneur #freelancer #virtualassistant #consultant | M96: graphics/video_covers/P-V19.png | N96: Draft
A97: 50 | B97: =IF($C$2="","",$C$2+A97-1) | C97: =IF(B97="","",TEXT(B97,"ddd")) | D97: Month 2: Product launch | E97: LinkedIn + Instagram | F97: Promotional post | G97: P-P08 | H97: Launch price ends tomorrow | K97: The launch code FOUNDING ends tomorrow, [LAUNCH END DATE]. After that, regular prices with no extension. If it fits how you work, now's the cheapest it'll be. If not, the free guides and starter kit aren't going anywhere. [STORE LINK] | L97: #bandofone #solopreneur #freelancer #virtualassistant #consultant | M97: graphics/promo_cards/P-P08.png | N97: Draft
A98: 50 | B98: =IF($C$2="","",$C$2+A98-1) | C98: =IF(B98="","",TEXT(B98,"ddd")) | D98: Month 2: Product launch | E98: TikTok / Reels / Shorts (+ LinkedIn native) | F98: Short video | G98: P-V20 | H98: Last full day of launch price | I98: Tomorrow's the last day of the launch price. | J98: /bundle/ | K98: The launch price (code FOUNDING) ends on [LAUNCH END DATE]. After that it's the regular price, with no extension. If it isn't for you, the free articles and starter kit are still there. | L98: #bandofone #solopreneur #freelancer #virtualassistant #consultant | M98: graphics/video_covers/P-V20.png | N98: Draft
A99: 51 | B99: =IF($C$2="","",$C$2+A99-1) | C99: =IF(B99="","",TEXT(B99,"ddd")) | D99: Month 2: Product launch | E99: LinkedIn + Instagram | F99: Promotional post | G99: P-P09 | H99: Last day | K99: Last day of launch pricing: code FOUNDING ends tonight. Thank you for following along this month. Tomorrow: back to free admin systems. [STORE LINK] | L99: #bandofone #solopreneur #freelancer #virtualassistant #consultant | M99: graphics/promo_cards/P-P09.png | N99: Draft
A100: 51 | B100: =IF($C$2="","",$C$2+A100-1) | C100: =IF(B100="","",TEXT(B100,"ddd")) | D100: Month 2: Product launch | E100: TikTok / Reels / Shorts (+ LinkedIn native) | F100: Short video | G100: P-V21 | H100: Final day | I100: Launch price ends tonight. | J100: /bundle/ | K100: Last day: code FOUNDING ends tonight ([LAUNCH END DATE]). Tomorrow we're back to free admin systems. Thanks for following the launch. | L100: #bandofone #solopreneur #freelancer #virtualassistant #consultant | M100: graphics/video_covers/P-V21.png | N100: Draft
A101: 52 | B101: =IF($C$2="","",$C$2+A101-1) | C101: =IF(B101="","",TEXT(B101,"ddd")) | D101: Month 2: Product launch | E101: Instagram | F101: Educational post (carousel) | G101: P-E12 | H101: Offboarding checklist | K101: How you finish decides whether they come back and refer you. Workflow 6 of The Solo Admin Playbook. | L101: #systemsthinking #SOP #productivitytips #solopreneur #businesssystems | M101: graphics/carousels/P-E12_01.png | N101: Draft
...

Sheet Summary
A1: Counts by type and status (formulas)
A3: Type | B3: Planned | C3: Posted | D3: Remaining
A4: Educational post | B4: =COUNTIF(Calendar!$F$5:$F$114,A4) -> 16 | C4: =COUNTIFS(Calendar!$F$5:$F$114,A4,Calendar!$N$5:$N$114,"Posted") -> 0 | D4: =B4-C4 -> 16
A5: Educational post (carousel) | B5: =COUNTIF(Calendar!$F$5:$F$114,A5) -> 14 | C5: =COUNTIFS(Calendar!$F$5:$F$114,A5,Calendar!$N$5:$N$114,"Posted") -> 0 | D5: =B5-C5 -> 14
A6: Promotional post | B6: =COUNTIF(Calendar!$F$5:$F$114,A6) -> 20 | C6: =COUNTIFS(Calendar!$F$5:$F$114,A6,Calendar!$N$5:$N$114,"Posted") -> 0 | D6: =B6-C6 -> 20
A7: Short video | B7: =COUNTIF(Calendar!$F$5:$F$114,A7) -> 60 | C7: =COUNTIFS(Calendar!$F$5:$F$114,A7,Calendar!$N$5:$N$114,"Posted") -> 0 | D7: =B7-C7 -> 60
A8: Total | B8: =SUM(B4:B7) -> 110 | C8: =SUM(C4:C7) -> 0 | D8: =SUM(D4:D7) -> 110
